{
  "drose": [
    [
      "Esta semana en @ NBAMEX: Nuevo capitulo en la carrera de @ drose https://mx.nba.com/news/nba-mexico-2018-2019-opinion-si-hay-espacio-para-una-gran-historia-de-redencion-me-gustaria-que-fuera-la-suya-evaristo-corona-derrick-rose/18l6815a7fd2m1sgt0372hoshx \u2026",
      {
        "neg": 0.0,
        "neu": 1.0,
        "pos": 0.0,
        "compound": 0.0
      }
    ],
    [
      "Drose looking like himself back in CHI town. 7-3 pointers",
      {
        "neg": 0.0,
        "neu": 0.783,
        "pos": 0.217,
        "compound": 0.3612
      }
    ],
    [
      "I never seen that video man wtf Bron do to Drose man",
      {
        "neg": 0.275,
        "neu": 0.725,
        "pos": 0.0,
        "compound": -0.5859
      }
    ],
    [
      "# drose # lonewolf Listen to Lone Wolf 25 by LiL Dero$$i # np on # SoundCloud https://soundcloud.com/cesarderossii_7/lone-wolf-25 \u2026",
      {
        "neg": 0.127,
        "neu": 0.727,
        "pos": 0.145,
        "compound": 0.0772
      }
    ],
    [
      "Good to see @ drose getting back to his best # NeverGiveUp",
      {
        "neg": 0.0,
        "neu": 0.53,
        "pos": 0.47,
        "compound": 0.7964
      }
    ],
    [
      "If only Jimmy were this humble and endearing. Go @ drose! A bright spot even with the mess around him. # twolvespleasefigurethismessouthttps://twitter.com/Timberwolves/status/1060991291868176384 \u2026",
      {
        "neg": 0.11,
        "neu": 0.749,
        "pos": 0.141,
        "compound": 0.1759
      }
    ],
    [
      "IF DROSE DONT WIN MIP THE NBA IS DOG SHIT",
      {
        "neg": 0.455,
        "neu": 0.545,
        "pos": 0.0,
        "compound": -0.7699
      }
    ],
    [
      "@ drose need at least 20 today 25 will make me happy tho",
      {
        "neg": 0.0,
        "neu": 0.748,
        "pos": 0.252,
        "compound": 0.5719
      }
    ],
    [
      "No # drose according to legal you\u2019re a # ROOKIE # language https://itunes.apple.com/us/album/veteran/378628955?i=378629279 \u2026",
      {
        "neg": 0.206,
        "neu": 0.654,
        "pos": 0.14,
        "compound": -0.1779
      }
    ],
    [
      "@ drose once you retire ima take yo spot maybe sooner though",
      {
        "neg": 0.0,
        "neu": 1.0,
        "pos": 0.0,
        "compound": 0.0
      }
    ],
    [
      "@ carmeloanthony my profile pic look like yo shot on chief @ drose what's good killa",
      {
        "neg": 0.0,
        "neu": 0.69,
        "pos": 0.31,
        "compound": 0.6597
      }
    ],
    [
      "Can my boy D rose get MIP I think he deserves it @ NBA @ drose",
      {
        "neg": 0.0,
        "neu": 1.0,
        "pos": 0.0,
        "compound": 0.0
      }
    ],
    [
      "Don't disrespect drose like that https://twitter.com/Crich901_/status/1061040008897937409 \u2026",
      {
        "neg": 0.25,
        "neu": 0.474,
        "pos": 0.276,
        "compound": 0.0572
      }
    ],
    [
      "drose like that ain\u2019t none of my business",
      {
        "neg": 0.0,
        "neu": 0.737,
        "pos": 0.263,
        "compound": 0.3612
      }
    ],
    [
      "might need the new twolves drose jersey",
      {
        "neg": 0.0,
        "neu": 1.0,
        "pos": 0.0,
        "compound": 0.0
      }
    ],
    [
      "All You Have to Do Is Look at the Data (MP, FGA, FGM, PPG) From the last 3 Seasons D\u2698 ( @ drose) Has Played... Including Both with the @ nyknicks & @ cavs in Order to See That He Has Been Back for at Least 3 Yrs. These Career Highs Are No Accident & Not New. The Data Supports This",
      {
        "neg": 0.092,
        "neu": 0.865,
        "pos": 0.043,
        "compound": -0.4215
      }
    ],
    [
      "Dez finna be the DRose of the NFL",
      {
        "neg": 0.0,
        "neu": 1.0,
        "pos": 0.0,
        "compound": 0.0
      }
    ],
    [
      "2. Note to @ 22wiggins : If you have the option to pass the ball to @ drose or Tyrus Jones (out of bounds or whatever) ALWAYS GIVE THE BALL TO YOUR MEAL TICKET @ DROSE !!",
      {
        "neg": 0.0,
        "neu": 1.0,
        "pos": 0.0,
        "compound": 0.0
      }
    ],
    [
      "1. I'm highly encouraged by @ 22wiggins & @ drose building chemistry last game. I'll be watching tonight to see if @ 22wiggins / @ drose builds off of that HIGH BASKETBALL IQ play from last game.",
      {
        "neg": 0.0,
        "neu": 0.848,
        "pos": 0.152,
        "compound": 0.6361
      }
    ],
    [
      "Keep an eye on @ drose tonight. The former MVP is hitting a career-high 46% of his threes and is posting the best effective field goal percentage of his 10-year career. https://www.sportsbettingdime.com/news/nba/timberwolves-vs-kings-player-props-fox-and-friends-edition/ \u2026",
      {
        "neg": 0.0,
        "neu": 0.793,
        "pos": 0.207,
        "compound": 0.8074
      }
    ],
    [
      "Shout out to @ drose @ ZionW32 @ RjBarrett6 & @ Cantguardmike in this one! We\u2019re back! https://twitter.com/RealRundown/status/1061034526737080322 \u2026",
      {
        "neg": 0.0,
        "neu": 1.0,
        "pos": 0.0,
        "compound": 0.0
      }
    ],
    [
      "Lol bron tryna break that mf Drose was doing to much https://twitter.com/L0RD_DiNER0/status/1060645325654888449 \u2026",
      {
        "neg": 0.0,
        "neu": 0.797,
        "pos": 0.203,
        "compound": 0.4215
      }
    ],
    [
      "The stuff about guys going under screens and him helping himself when opponents do that sounds almost IDENTICAL to what he said years ago after dropping 44 on the Hawks in the Semis... I\u2019m HAUNTED by how much # DRose seems back. Give \u2018em hell Derrick. https://twitter.com/Timberwolves/status/1060991291868176384 \u2026",
      {
        "neg": 0.157,
        "neu": 0.802,
        "pos": 0.041,
        "compound": -0.8038
      }
    ],
    [
      "@ chicagobulls make sure y\u2019all ready to make a pitch to DRose this summer.",
      {
        "neg": 0.0,
        "neu": 0.676,
        "pos": 0.324,
        "compound": 0.5859
      }
    ],
    [
      "I like where we are with our front court tbh. Wouldn\u2019t want to make changes to it buttttt idk it\u2019s AD. First things first, sign DRose next summer and a good ass SF who can play on both sides of the ball.",
      {
        "neg": 0.102,
        "neu": 0.708,
        "pos": 0.19,
        "compound": 0.4939
      }
    ],
    [
      "vitamin drose lol",
      {
        "neg": 0.0,
        "neu": 0.167,
        "pos": 0.833,
        "compound": 0.6124
      }
    ],
    [
      "Drose still got that killa!!",
      {
        "neg": 0.0,
        "neu": 1.0,
        "pos": 0.0,
        "compound": 0.0
      }
    ],
    [
      "Carmelo* but I see your point",
      {
        "neg": 0.0,
        "neu": 1.0,
        "pos": 0.0,
        "compound": 0.0
      }
    ],
    [
      "You can take drose out Chicago but you can't take the Chicago out Drose",
      {
        "neg": 0.0,
        "neu": 1.0,
        "pos": 0.0,
        "compound": 0.0
      }
    ],
    [
      "Tu sais m\u00eame pas jou\u00e9 sur le terrain Brother",
      {
        "neg": 0.0,
        "neu": 1.0,
        "pos": 0.0,
        "compound": 0.0
      }
    ],
    [
      "At this point im DRose",
      {
        "neg": 0.0,
        "neu": 1.0,
        "pos": 0.0,
        "compound": 0.0
      }
    ],
    [
      "True. But all I wanted to say is that u dont wanna injure your man, use him smartly. If he wouldnt have a history of injuries, hed be playing 42 pero game lmao",
      {
        "neg": 0.0,
        "neu": 0.672,
        "pos": 0.328,
        "compound": 0.9136
      }
    ],
    [
      "Keep That Intensity High. @ drose",
      {
        "neg": 0.0,
        "neu": 1.0,
        "pos": 0.0,
        "compound": 0.0
      }
    ],
    [
      "@ drose @ oMgitsTTF I always had a feeling drose would make a come back just to good of a player. I understand injuries could take anybodies career but glad to see drose playing some good basketball right now. Keep up the hard work",
      {
        "neg": 0.035,
        "neu": 0.676,
        "pos": 0.289,
        "compound": 0.8922
      }
    ],
    [
      "",
      {
        "neg": 0.0,
        "neu": 0.0,
        "pos": 0.0,
        "compound": 0.0
      }
    ],
    [
      "@ JimmyButler",
      {
        "neg": 0.0,
        "neu": 1.0,
        "pos": 0.0,
        "compound": 0.0
      }
    ],
    [
      "Dev the enemy of redundant tweets",
      {
        "neg": 0.412,
        "neu": 0.588,
        "pos": 0.0,
        "compound": -0.5423
      }
    ],
    [
      "This game ain\u2019t built for us to win bro",
      {
        "neg": 0.0,
        "neu": 0.678,
        "pos": 0.322,
        "compound": 0.5859
      }
    ],
    [
      "You right you right. They have every size but mine tho",
      {
        "neg": 0.0,
        "neu": 1.0,
        "pos": 0.0,
        "compound": 0.0
      }
    ],
    [
      "DRose joint man I\u2019m sooooo sick https://twitter.com/Timberwolves/status/1060923169341693953 \u2026",
      {
        "neg": 0.355,
        "neu": 0.645,
        "pos": 0.0,
        "compound": -0.5106
      }
    ],
    [
      "Hemos elegido la misma!!!!",
      {
        "neg": 0.0,
        "neu": 1.0,
        "pos": 0.0,
        "compound": 0.0
      }
    ],
    [
      "drose playing my career in real life https://twitter.com/ryan_welch20/status/1060961334014238720 \u2026",
      {
        "neg": 0.0,
        "neu": 0.795,
        "pos": 0.205,
        "compound": 0.2023
      }
    ],
    [
      "Bro you really thought you was gonna just order this joint with ease? Cmon sonpic.twitter.com/ygdyO2qhBD",
      {
        "neg": 0.0,
        "neu": 0.848,
        "pos": 0.152,
        "compound": 0.3612
      }
    ],
    [
      "Hey what program did you use to replace the main video with DRose's face?",
      {
        "neg": 0.0,
        "neu": 1.0,
        "pos": 0.0,
        "compound": 0.0
      }
    ],
    [
      "Order of Greatness defined by surrounding teammates, size, and effort: 1 - DRose 2 - BGriffin 3 - SCurry 4 - KThompson",
      {
        "neg": 0.0,
        "neu": 1.0,
        "pos": 0.0,
        "compound": 0.0
      }
    ],
    [
      "Support your teammates. It\u2019s not about you. Lead by example. Understand your role. Communicate. Man, he lays it all out so effortlessly. Thank you @ drose for being an awesome example of leadership in a time we really need it! # AllEyesNorthhttps://twitter.com/Timberwolves/status/1060991291868176384 \u2026",
      {
        "neg": 0.0,
        "neu": 0.785,
        "pos": 0.215,
        "compound": 0.8711
      }
    ],
    [
      "Pretty classy @ drose....o and you lose that game to those weak ass lakers....js..hahaha https://twitter.com/gifdsports/status/1060397048070049793 \u2026",
      {
        "neg": 0.376,
        "neu": 0.372,
        "pos": 0.252,
        "compound": -0.4588
      }
    ],
    [
      "They got a DRose one?",
      {
        "neg": 0.0,
        "neu": 1.0,
        "pos": 0.0,
        "compound": 0.0
      }
    ],
    [
      "Listen to Tunnel Vision Ash x Drose by AshKash # np on # SoundCloud https://soundcloud.com/ashhhh6/tunnel-vision-ash-x-drose \u2026",
      {
        "neg": 0.0,
        "neu": 0.694,
        "pos": 0.306,
        "compound": 0.5267
      }
    ],
    [
      "New drose** https://twitter.com/MELOD1P/status/1060408072990937088 \u2026",
      {
        "neg": 0.0,
        "neu": 1.0,
        "pos": 0.0,
        "compound": 0.0
      }
    ],
    [
      "Derrick Rose: OK spot but counting on drose for 36 points on a regular basis has not worked out well for anyone in the long run. Fading but with a heavy heart, I you drose, it's just math. pic.twitter.com/pLHW2Jq3mM",
      {
        "neg": 0.058,
        "neu": 0.89,
        "pos": 0.051,
        "compound": -0.0656
      }
    ],
    [
      "@ austineiter1 @ DunkingWolvesFS @ TimberwolvesRZ @ NBCSBulls @ BullsSource @ chicagobulls @ NBCSChicago @ drose How about this bring Rose back where he belongs keep him there his child hood home",
      {
        "neg": 0.0,
        "neu": 1.0,
        "pos": 0.0,
        "compound": 0.0
      }
    ],
    [
      "Drose is nice",
      {
        "neg": 0.0,
        "neu": 0.417,
        "pos": 0.583,
        "compound": 0.4215
      }
    ],
    [
      "Often times I'm reminded of when I put up 25 in a Men's League Basketball game. That was out of my prime. I feel like I'm the legend @ drose is.",
      {
        "neg": 0.0,
        "neu": 0.912,
        "pos": 0.088,
        "compound": 0.3612
      }
    ],
    [
      "Drose plays 5 more games almost like the ones he did against LA he's back!!!",
      {
        "neg": 0.0,
        "neu": 0.692,
        "pos": 0.308,
        "compound": 0.6538
      }
    ],
    [
      "Floor seats newyears eve l gotta tell my nigga DRose keep it up , he need to hear that from me",
      {
        "neg": 0.0,
        "neu": 1.0,
        "pos": 0.0,
        "compound": 0.0
      }
    ],
    [
      "My Nigga @ drose been eating https://twitter.com/ComplexSports/status/1060658433710530562 \u2026",
      {
        "neg": 0.0,
        "neu": 1.0,
        "pos": 0.0,
        "compound": 0.0
      }
    ],
    [
      "@ xxxtentacion @ lilpump @goSwaeLee # XXXTentacion # lilpump # swaelee # armsaroundyou # drose # powerglide # RLMIAV # RIPX # LLJ # RIPXXXTentacion # makeouthill # LilPeepForeverpic.twitter.com/PCafDMA2mf",
      {
        "neg": 0.0,
        "neu": 1.0,
        "pos": 0.0,
        "compound": 0.0
      }
    ],
    [
      "I\u2019m so glad that @ drose is back. He always had it. Keep cooking em\u2019",
      {
        "neg": 0.0,
        "neu": 0.798,
        "pos": 0.202,
        "compound": 0.5095
      }
    ],
    [
      "Story of my life man who has the plug on this @ drose jersey in a 44?? pic.twitter.com/0LLrgyCRDF",
      {
        "neg": 0.0,
        "neu": 1.0,
        "pos": 0.0,
        "compound": 0.0
      }
    ],
    [
      "I wonder what Charles Barkley Shaw and all those other drose haters have to say now",
      {
        "neg": 0.186,
        "neu": 0.814,
        "pos": 0.0,
        "compound": -0.4939
      }
    ],
    [
      "@ drose https://twitter.com/i/moments/1060417058746249217 \u2026",
      {
        "neg": 0.0,
        "neu": 1.0,
        "pos": 0.0,
        "compound": 0.0
      }
    ],
    [
      "Welcome Back @ drose , the game has missed you!! Now the real fans will watch and applaud as you continue to torch every doubt and hate that has been spewed your way. # WinnersNeverQuit # StopTheHate # drose @ Timberwolves @ NBA @ espn @ BleacherReport @ RachelNichols1pic.twitter.com/oUsL1RUloF",
      {
        "neg": 0.183,
        "neu": 0.694,
        "pos": 0.122,
        "compound": -0.4559
      }
    ],
    [
      "Marry me",
      {
        "neg": 0.0,
        "neu": 1.0,
        "pos": 0.0,
        "compound": 0.0
      }
    ],
    [
      "DRose over there like \u2018let these niggas beef I\u2019m ballin right now\u2019 pic.twitter.com/wOIZOnYoui",
      {
        "neg": 0.151,
        "neu": 0.692,
        "pos": 0.157,
        "compound": 0.0258
      }
    ],
    [
      "In the midst of a career resurgence, @ drose ($6K) makes for a great play with Jeff Teague still out for the @ Timberwolves. Where else should you turn for tonight's seven-game slate? NBA DFS Helper ($) https://bit.ly/2QyvjRC pic.twitter.com/H3dmUZrm80",
      {
        "neg": 0.0,
        "neu": 0.782,
        "pos": 0.218,
        "compound": 0.836
      }
    ],
    [
      "My man @ drose is heating up pic.twitter.com/IOKW5naTZR",
      {
        "neg": 0.0,
        "neu": 1.0,
        "pos": 0.0,
        "compound": 0.0
      }
    ],
    [
      "Bhahaha that\u2019s some DRose right there",
      {
        "neg": 0.0,
        "neu": 1.0,
        "pos": 0.0,
        "compound": 0.0
      }
    ],
    [
      "Damn same age as DRose",
      {
        "neg": 0.403,
        "neu": 0.597,
        "pos": 0.0,
        "compound": -0.4019
      }
    ],
    [
      "How the fuck!?! Y'all fuckin bandwagonerrsss left me without a jersey need a throwback jersey or city edition jersey of @ drose ASAP!!!! @ Timberwolves @ NBApic.twitter.com/84XvgxZ22Q",
      {
        "neg": 0.182,
        "neu": 0.818,
        "pos": 0.0,
        "compound": -0.6876
      }
    ],
    [
      "@ drose fr needs to reach out to @ DezBryant ASAP",
      {
        "neg": 0.0,
        "neu": 0.879,
        "pos": 0.121,
        "compound": 0.0258
      }
    ],
    [
      "I don't like Brown. Not really a safe lineup for cash imo. I played around, keeping some of your core and came up with Kemba, DRose, Ellington, Levert, Prince, JRich, Morris, Gordon, Allen.",
      {
        "neg": 0.139,
        "neu": 0.791,
        "pos": 0.07,
        "compound": -0.3254
      }
    ],
    [
      "He's like a reverse Carmello",
      {
        "neg": 0.0,
        "neu": 0.545,
        "pos": 0.455,
        "compound": 0.3612
      }
    ],
    [
      "Dez came back with the Drose knees pic.twitter.com/IC9vlJWfJu",
      {
        "neg": 0.0,
        "neu": 1.0,
        "pos": 0.0,
        "compound": 0.0
      }
    ],
    [
      "50 pts record en carri\u00e8re, voici comment DRose a sign\u00e9 son retour en NBA apr\u00e8s 7 ans de gal\u00e8re. Pour @ VGordon3000 la perf est admirable mais il ne faut pas s\u2019enflammer quand au retour au top du meneur des Wolves. La suite dans l\u2019\u00e9pisode 15 du MoneyTime. https://soundcloud.com/moneytimepodcast/mt15-lesproblemes/s-gYzgd \u2026pic.twitter.com/2lLijp1gvQ",
      {
        "neg": 0.0,
        "neu": 0.893,
        "pos": 0.107,
        "compound": 0.6597
      }
    ],
    [
      "The fact that he said 'thank you' after being complimented speaks volumes about where he is as a person. You don't see that often in pro sports. Great to see.",
      {
        "neg": 0.0,
        "neu": 0.734,
        "pos": 0.266,
        "compound": 0.8555
      }
    ],
    [
      "I see you out here. @ drose with the 2 step. Classic material!",
      {
        "neg": 0.0,
        "neu": 1.0,
        "pos": 0.0,
        "compound": 0.0
      }
    ],
    [
      "Please support my GoFundMe campaign: https://www.gofundme.com/get-jamir-to-school?pc=tw_co_dashboard_a&rcid=cbf1173996184733b5830eea09ccbca3 \u2026 @ gofundme @ trvsXX @ kingjames @ drose @ isaiahthomas @ kyrieirving",
      {
        "neg": 0.0,
        "neu": 0.667,
        "pos": 0.333,
        "compound": 0.6124
      }
    ],
    [
      "G",
      {
        "neg": 0.0,
        "neu": 0.0,
        "pos": 0.0,
        "compound": 0.0
      }
    ],
    [
      "That Drose",
      {
        "neg": 0.0,
        "neu": 1.0,
        "pos": 0.0,
        "compound": 0.0
      }
    ],
    [
      "Lmao Niggas saying Lonzo Dodging Fox like He ain\u2019t played against Dame and DRose just nights before https://twitter.com/LakersReporter/status/1060996740378058752 \u2026",
      {
        "neg": 0.148,
        "neu": 0.508,
        "pos": 0.344,
        "compound": 0.7184
      }
    ],
    [
      "Besides DRose, one of my all-time \u201cwhat-if\u201d dudes that could get buckets https://twitter.com/SLAMonline/status/1060979682038988801 \u2026",
      {
        "neg": 0.0,
        "neu": 1.0,
        "pos": 0.0,
        "compound": 0.0
      }
    ],
    [
      "So much respect for this man @ drose https://twitter.com/Timberwolves/status/1060991291868176384 \u2026",
      {
        "neg": 0.0,
        "neu": 0.674,
        "pos": 0.326,
        "compound": 0.5233
      }
    ],
    [
      "@ NBA2K when are y\u2019all gone update @ drose 2k rating?",
      {
        "neg": 0.0,
        "neu": 1.0,
        "pos": 0.0,
        "compound": 0.0
      }
    ],
    [
      "Drose likes chic fil a tho",
      {
        "neg": 0.0,
        "neu": 0.38,
        "pos": 0.62,
        "compound": 0.5994
      }
    ],
    [
      "We won\u2019t make playoffs with teague starting and doing nothing for the team",
      {
        "neg": 0.0,
        "neu": 1.0,
        "pos": 0.0,
        "compound": 0.0
      }
    ],
    [
      "He shouldnt, lets let him get that 6th man and rest up a bit for these playoffs",
      {
        "neg": 0.0,
        "neu": 1.0,
        "pos": 0.0,
        "compound": 0.0
      }
    ],
    [
      "Why they selling a Jimmy Butler jersey instead of Drose? He gone get traded anyway.",
      {
        "neg": 0.0,
        "neu": 1.0,
        "pos": 0.0,
        "compound": 0.0
      }
    ],
    [
      "Minnesota, D. Rose jersey, to be specific @ drose",
      {
        "neg": 0.0,
        "neu": 1.0,
        "pos": 0.0,
        "compound": 0.0
      }
    ],
    [
      "This is what a leader looks like",
      {
        "neg": 0.0,
        "neu": 0.667,
        "pos": 0.333,
        "compound": 0.3612
      }
    ],
    [
      "Drose dropped 50 my guy https://twitter.com/_fellyy/status/1060977708572856320 \u2026",
      {
        "neg": 0.0,
        "neu": 1.0,
        "pos": 0.0,
        "compound": 0.0
      }
    ],
    [
      "Nah fam you\u2019re here to get buckets cause everyone else actin weak",
      {
        "neg": 0.301,
        "neu": 0.699,
        "pos": 0.0,
        "compound": -0.5106
      }
    ],
    [
      "# Humble",
      {
        "neg": 0.0,
        "neu": 1.0,
        "pos": 0.0,
        "compound": 0.0
      }
    ],
    [
      "He better be starting over teague",
      {
        "neg": 0.0,
        "neu": 0.633,
        "pos": 0.367,
        "compound": 0.4404
      }
    ],
    [
      "\"I\u2019m here just to help the guys. I\u2019m not trying to step on nobody\u2019s toes. I know my role being here, and that\u2019s to try to lead by example and be in guys\u2019 ear whenever I get a chance.\" -- @ drose pic.twitter.com/PdBuAN3RLt",
      {
        "neg": 0.0,
        "neu": 0.934,
        "pos": 0.066,
        "compound": 0.4019
      }
    ],
    [
      "Drose, John Wall, Fox Coach Cal be doing his thing https://twitter.com/CourtsideFilms/status/1060569401005629441 \u2026",
      {
        "neg": 0.0,
        "neu": 1.0,
        "pos": 0.0,
        "compound": 0.0
      }
    ],
    [
      "We got tits? Seems like an odd thing for one to say out loud... but good for you @ drose for knowing that indeed Men do as well.",
      {
        "neg": 0.093,
        "neu": 0.66,
        "pos": 0.247,
        "compound": 0.7311
      }
    ],
    [
      "Found myself going thru the details of the drose case after being irked at how flippantly ppl calling this man a rapist off of shit that dont prove anything. Not saying he's absolutely innocent but as far as I can tell, her lawyers didnt have enough evidence far as I'm concerned",
      {
        "neg": 0.099,
        "neu": 0.866,
        "pos": 0.035,
        "compound": -0.5273
      }
    ],
    [
      "Drose",
      {
        "neg": 0.0,
        "neu": 1.0,
        "pos": 0.0,
        "compound": 0.0
      }
    ],
    [
      "Drose preferably on fd at his price or suppose... What do you think of dwight going back to Orlando tonight?",
      {
        "neg": 0.0,
        "neu": 1.0,
        "pos": 0.0,
        "compound": 0.0
      }
    ],
    [
      "Drose me w.e you and Zach baking Marv or Kyle https://twitter.com/WWNNN_Kurtis/status/1060977673546203136 \u2026",
      {
        "neg": 0.0,
        "neu": 1.0,
        "pos": 0.0,
        "compound": 0.0
      }
    ],
    [
      "Where do the drose injuries rank among the NBA\u2019s top \u201cwhat-ifs?\u201d Maybe @ BillSimmons would know.",
      {
        "neg": 0.0,
        "neu": 0.886,
        "pos": 0.114,
        "compound": 0.2023
      }
    ],
    [
      "Drose slanderers all look the same https://twitter.com/DuncanSmithNBA/status/1060617355917701120 \u2026",
      {
        "neg": 0.0,
        "neu": 1.0,
        "pos": 0.0,
        "compound": 0.0
      }
    ],
    [
      "My first pair of @ drose lasted a good lil minute lol",
      {
        "neg": 0.0,
        "neu": 0.584,
        "pos": 0.416,
        "compound": 0.6908
      }
    ],
    [
      "@ drose should win Comeback player of the year & 6th man Award",
      {
        "neg": 0.0,
        "neu": 0.552,
        "pos": 0.448,
        "compound": 0.8074
      }
    ],
    [
      "Boy tryna pull off a Monstars on you DRose be careful https://twitter.com/KarlTowns/status/1057852005669056512 \u2026",
      {
        "neg": 0.0,
        "neu": 0.862,
        "pos": 0.138,
        "compound": 0.1531
      }
    ],
    [
      "Once jimmy leaves MN, yes. But maybe we lost the drose injury?",
      {
        "neg": 0.38,
        "neu": 0.514,
        "pos": 0.106,
        "compound": -0.7003
      }
    ],
    [
      "Ojala no se lesione. Me encanta DRose",
      {
        "neg": 0.268,
        "neu": 0.732,
        "pos": 0.0,
        "compound": -0.296
      }
    ],
    [
      "kiss and make up dinlerken drose highlight izlemek i\u015fte best couple",
      {
        "neg": 0.0,
        "neu": 0.46,
        "pos": 0.54,
        "compound": 0.8555
      }
    ],
    [
      "Abi sende m\u00fcslumans\u0131n evim yok bi daire paras\u0131 yollarm\u0131s\u0131n T\u00fcrk paras\u0131yla en fazla 120 bin TL abi evlenecem ev lazm",
      {
        "neg": 0.0,
        "neu": 1.0,
        "pos": 0.0,
        "compound": 0.0
      }
    ],
    [
      "Can we sacrifice KAT to the basketball gods to make sure DRose stays healthy and prosperous please?",
      {
        "neg": 0.0,
        "neu": 0.556,
        "pos": 0.444,
        "compound": 0.8555
      }
    ],
    [
      "Reminds you of Drose",
      {
        "neg": 0.0,
        "neu": 1.0,
        "pos": 0.0,
        "compound": 0.0
      }
    ],
    [
      "@ drose My mom told me that for my birthday she would take me to one of your games because my first and only basketball game i went to was a bulls game, but at the time you were traded. so i hope i can come back home to Chicago area. And to hopefully meet you and hangout.",
      {
        "neg": 0.0,
        "neu": 0.855,
        "pos": 0.145,
        "compound": 0.8645
      }
    ],
    [
      "@ drose I just want to get to meet you derrick your my favorite, I prayed for you to rise above everyone's hate and little by little your proving everyone wrong! I hope that i go back and live with my mom this winter.",
      {
        "neg": 0.141,
        "neu": 0.704,
        "pos": 0.155,
        "compound": -0.2244
      }
    ],
    [
      "Free Drose",
      {
        "neg": 0.0,
        "neu": 0.233,
        "pos": 0.767,
        "compound": 0.5106
      }
    ],
    [
      "@ drose Derrick congrats on your career high 50 point game on Halloween, unfortunately i missed it because im living with my dad now and he doesn't have TV out here so i couldn't see you play. I never gave up on you even when people told me to give up on you, i never did.",
      {
        "neg": 0.116,
        "neu": 0.824,
        "pos": 0.06,
        "compound": -0.304
      }
    ],
    [
      "Ur not his friend",
      {
        "neg": 0.467,
        "neu": 0.533,
        "pos": 0.0,
        "compound": -0.3875
      }
    ],
    [
      "Stephen a smith said drose is back to being a star",
      {
        "neg": 0.0,
        "neu": 1.0,
        "pos": 0.0,
        "compound": 0.0
      }
    ],
    [
      "Fire up KAT and DRose?",
      {
        "neg": 0.375,
        "neu": 0.625,
        "pos": 0.0,
        "compound": -0.34
      }
    ],
    [
      "Ah i didn\u2019t see that game so i can\u2019t speak upon it but I\u2019m sure drose dropping 50 made that possible",
      {
        "neg": 0.0,
        "neu": 0.859,
        "pos": 0.141,
        "compound": 0.4497
      }
    ],
    [
      "T\u00e1 certo, vou comprar Aql retro da Nike do wolves q o drose marcou 50 pra",
      {
        "neg": 0.0,
        "neu": 1.0,
        "pos": 0.0,
        "compound": 0.0
      }
    ],
    [
      "@ drose",
      {
        "neg": 0.0,
        "neu": 1.0,
        "pos": 0.0,
        "compound": 0.0
      }
    ],
    [
      "these are the numbers and success real niggas was waiting from DRose for the last 6-7 years . this is really what we stan https://twitter.com/TheHoopCentral/status/1060704010183692289 \u2026",
      {
        "neg": 0.085,
        "neu": 0.783,
        "pos": 0.132,
        "compound": 0.3182
      }
    ],
    [
      "@ drose YOU BEEN BALLIN https://twitter.com/BleacherReport/status/1060564822767616000 \u2026",
      {
        "neg": 0.0,
        "neu": 1.0,
        "pos": 0.0,
        "compound": 0.0
      }
    ],
    [
      "DRose dropping 40 tonight",
      {
        "neg": 0.0,
        "neu": 1.0,
        "pos": 0.0,
        "compound": 0.0
      }
    ],
    [
      "So for the rest of the season, I am going to be watching the timberwolves games as my second team. Need to watch how Drose wins the MIP!",
      {
        "neg": 0.0,
        "neu": 0.867,
        "pos": 0.133,
        "compound": 0.6114
      }
    ],
    [
      "Jordan y DRose pa cuando tenia la rodilla como jam\u00f3n https://twitter.com/_Anuel_AA/status/1060652248290586624 \u2026",
      {
        "neg": 0.0,
        "neu": 1.0,
        "pos": 0.0,
        "compound": 0.0
      }
    ],
    [
      "Cal had all his wins from the year with DRose vacated and that Zona story that ESPN reported has so many hole that no other network believes it",
      {
        "neg": 0.069,
        "neu": 0.815,
        "pos": 0.116,
        "compound": 0.3612
      }
    ],
    [
      "He absorbed this nigga powers, keep an eye on dRose knees after this... https://twitter.com/L0RD_DiNER0/status/1060645325654888449 \u2026",
      {
        "neg": 0.0,
        "neu": 1.0,
        "pos": 0.0,
        "compound": 0.0
      }
    ],
    [
      "Third parties spent big bucks in Facebook ads in Wisconsin gubernatorial, senate races http://bit.ly/2JL9vPX # performancemarketing # googleads # paidads # facebookads via @ drose",
      {
        "neg": 0.0,
        "neu": 0.876,
        "pos": 0.124,
        "compound": 0.4019
      }
    ],
    [
      "Got that DRose step! @ AyoDos_11 nice start to the season!",
      {
        "neg": 0.0,
        "neu": 0.727,
        "pos": 0.273,
        "compound": 0.5242
      }
    ],
    [
      "Would you like to see DRose retire a Bull? Derrick has been in his bag lately @ eg.studiospic.twitter.com/rBdsqNdNyO",
      {
        "neg": 0.0,
        "neu": 0.857,
        "pos": 0.143,
        "compound": 0.3612
      }
    ],
    [
      "Aye why drose curve him like that? LeBron like \u201cyou tryna steal my MVP again nigga!\u201d https://twitter.com/reckless_mall/status/1060635926433554432 \u2026",
      {
        "neg": 0.142,
        "neu": 0.622,
        "pos": 0.235,
        "compound": 0.2714
      }
    ],
    [
      "\"Why not me?\" @ drose can be a @ NBA MVP again, if given the chance. Love him! He really represented the people of # Chicago when he's with the @ chicagobulls . # BeProud # BeHumble # BeThankful # GodBlesshttps://twitter.com/NBCSBulls/status/1060408464323813376 \u2026",
      {
        "neg": 0.0,
        "neu": 0.817,
        "pos": 0.183,
        "compound": 0.7574
      }
    ],
    [
      "I Swore His Clothes & Shit Ain\u2019t Drop Till 2012",
      {
        "neg": 0.487,
        "neu": 0.513,
        "pos": 0.0,
        "compound": -0.6908
      }
    ],
    [
      "chill jojo respect drose",
      {
        "neg": 0.0,
        "neu": 0.492,
        "pos": 0.508,
        "compound": 0.4767
      }
    ],
    [
      "Everybody back on drose bandwagon again now fuck y\u2019all",
      {
        "neg": 0.304,
        "neu": 0.696,
        "pos": 0.0,
        "compound": -0.5423
      }
    ],
    [
      "@ drose better be in the all-star game. I really want to see him play in it",
      {
        "neg": 0.0,
        "neu": 0.635,
        "pos": 0.365,
        "compound": 0.7089
      }
    ],
    [
      "mdrrr et pk t'es un fan de drose toi tu suivais la nba a l'ancienne ?",
      {
        "neg": 0.0,
        "neu": 0.85,
        "pos": 0.15,
        "compound": 0.3182
      }
    ],
    [
      "Zion Williamson is 6'7\", weighs as much as JJ Watt and has the same vertical as DRose in his prime pic.twitter.com/2HO2LpUARl",
      {
        "neg": 0.0,
        "neu": 0.88,
        "pos": 0.12,
        "compound": 0.4084
      }
    ],
    [
      "Happy to DRose back in form. https://twitter.com/gifdsports/status/1060397048070049793 \u2026",
      {
        "neg": 0.0,
        "neu": 0.619,
        "pos": 0.381,
        "compound": 0.5719
      }
    ],
    [
      "@ drose watching you this year is great man. We all get so happy to see you enjoy the game!",
      {
        "neg": 0.0,
        "neu": 0.565,
        "pos": 0.435,
        "compound": 0.9236
      }
    ],
    [
      "@ drose man! you are still the best NBA player for me! congrats! soar high idol. so proud of you! God bless.",
      {
        "neg": 0.0,
        "neu": 0.475,
        "pos": 0.525,
        "compound": 0.9562
      }
    ],
    [
      "@ drose gets all my respect",
      {
        "neg": 0.0,
        "neu": 0.563,
        "pos": 0.437,
        "compound": 0.4767
      }
    ],
    [
      "Forget winning 6th man of the year, @ drose got MVP in the bag!!! Been through a lot, but also conquered more than a lot. A rose's rarest essence lives within the thorn. But he that dares not grasp the thorn, should never crave the rose # AllStar # MVPhttps://twitter.com/NBATV/status/1060575372167782401 \u2026",
      {
        "neg": 0.031,
        "neu": 0.903,
        "pos": 0.066,
        "compound": 0.3871
      }
    ],
    [
      "DRose PER is currently 19.7 which is 7th among SGs, 10th among PGs and the only one on list to average under 30 mins per game. His 3rd highest rating of career. Higher than his 2nd year when he was an All-star starter.",
      {
        "neg": 0.0,
        "neu": 1.0,
        "pos": 0.0,
        "compound": 0.0
      }
    ],
    [
      "@ Nike @ nikebasketball Where can I get @ drose 2018 city edition jersey? I know he has to have one!",
      {
        "neg": 0.0,
        "neu": 1.0,
        "pos": 0.0,
        "compound": 0.0
      }
    ],
    [
      "Need an SGA, Bev, Tobi, Lou, DLo, Melo, DWade, and a DRose jersey. that\u2019s way too much, I\u2019ll just take a DLo and be on my way.",
      {
        "neg": 0.0,
        "neu": 1.0,
        "pos": 0.0,
        "compound": 0.0
      }
    ],
    [
      "# NBA\u2502 @ KingJames Trying To Get Some Of That @ drose Magic pic.twitter.com/vlDTN0BfBe",
      {
        "neg": 0.0,
        "neu": 1.0,
        "pos": 0.0,
        "compound": 0.0
      }
    ],
    [
      "# NBAEn5x5 @ 5x5_basket Ayer le gan\u00f3 @ okcthunder a @ HoustonRockets @ celtics dio vuelta un partido que perd\u00eda por +20. Y perdieron los @ warriors a mano de Giannis y sus @ Bucks Gracias Rulo por tu imagen, ayer no pusiste nada de DRose. pic.twitter.com/2ZFgcWUtb7",
      {
        "neg": 0.059,
        "neu": 0.941,
        "pos": 0.0,
        "compound": -0.296
      }
    ],
    [
      "# NBA\u2502 @ KingJames Trying To Get Some Of That @ drose Magic pic.twitter.com/bU1IYFUh1A",
      {
        "neg": 0.0,
        "neu": 1.0,
        "pos": 0.0,
        "compound": 0.0
      }
    ],
    [
      "Jimmy and DRose doin it on they own https://twitter.com/Cindtrillella/status/1060407125271289858 \u2026",
      {
        "neg": 0.0,
        "neu": 1.0,
        "pos": 0.0,
        "compound": 0.0
      }
    ],
    [
      "@ drose from 9ish years ago. Still have it! pic.twitter.com/D57RLfiYLM",
      {
        "neg": 0.0,
        "neu": 1.0,
        "pos": 0.0,
        "compound": 0.0
      }
    ],
    [
      "@ MNWolvesStore when will the DRose city edition purple jersey get restocked? I fell asleep before the drop",
      {
        "neg": 0.123,
        "neu": 0.877,
        "pos": 0.0,
        "compound": -0.2732
      }
    ],
    [
      "@ drose pic.twitter.com/wHDSOTIAWR",
      {
        "neg": 0.0,
        "neu": 1.0,
        "pos": 0.0,
        "compound": 0.0
      }
    ],
    [
      "Yeah im all in on drose again lmao",
      {
        "neg": 0.0,
        "neu": 0.496,
        "pos": 0.504,
        "compound": 0.7269
      }
    ],
    [
      "We're all waiting on a DRose classic jersey. Get sewing!",
      {
        "neg": 0.0,
        "neu": 1.0,
        "pos": 0.0,
        "compound": 0.0
      }
    ],
    [
      "Catastrophique c\u2019est gentil encore",
      {
        "neg": 0.0,
        "neu": 1.0,
        "pos": 0.0,
        "compound": 0.0
      }
    ],
    [
      "Did you see the price jump on rozier he\u2019s more expensive then drose on FD",
      {
        "neg": 0.0,
        "neu": 1.0,
        "pos": 0.0,
        "compound": 0.0
      }
    ],
    [
      "Czas na collab ;) haha",
      {
        "neg": 0.0,
        "neu": 0.38,
        "pos": 0.62,
        "compound": 0.5994
      }
    ],
    [
      "I love watching DRose play the way he is can this keep up please?",
      {
        "neg": 0.0,
        "neu": 0.529,
        "pos": 0.471,
        "compound": 0.836
      }
    ],
    [
      "Bro DRose used to piss Bron off lol https://twitter.com/ThrowbackHoops/status/1060405613459468288 \u2026",
      {
        "neg": 0.216,
        "neu": 0.56,
        "pos": 0.224,
        "compound": 0.0258
      }
    ],
    [
      "Dawg I love both of them so much. It\u2019s amazing seeing DRose hoop like this again.",
      {
        "neg": 0.0,
        "neu": 0.527,
        "pos": 0.473,
        "compound": 0.8948
      }
    ],
    [
      "Earl the drose of the rap game",
      {
        "neg": 0.0,
        "neu": 1.0,
        "pos": 0.0,
        "compound": 0.0
      }
    ],
    [
      "Save a men's large for me! I get out of school at 2:30",
      {
        "neg": 0.0,
        "neu": 0.741,
        "pos": 0.259,
        "compound": 0.5411
      }
    ],
    [
      "# purplerain # drose @Texas https://www.instagram.com/p/Bp958yeB6Jn/?utm_source=ig_twitter_share&igshid=1w63uxbfbe1kj \u2026",
      {
        "neg": 0.0,
        "neu": 1.0,
        "pos": 0.0,
        "compound": 0.0
      }
    ],
    [
      "I need one",
      {
        "neg": 0.0,
        "neu": 1.0,
        "pos": 0.0,
        "compound": 0.0
      }
    ],
    [
      "@ lino93420 @ Djailson_Drose elle a pas essay\u00e9 de faire sa l\u2019autre go au bar",
      {
        "neg": 0.0,
        "neu": 1.0,
        "pos": 0.0,
        "compound": 0.0
      }
    ],
    [
      "seeing drose playing this good means good times are coming",
      {
        "neg": 0.0,
        "neu": 0.45,
        "pos": 0.55,
        "compound": 0.8201
      }
    ],
    [
      "No DRose? # ThatsDeep",
      {
        "neg": 0.524,
        "neu": 0.476,
        "pos": 0.0,
        "compound": -0.296
      }
    ],
    [
      "I suppose that\u2019s another reason why he was so emotional that night. He knows that even though he\u2019s been working amazingly hard people still aren\u2019t checkin for him like they used to. He\u2019s MAKING them put some \u201crespeck\u201d on his name.pic.twitter.com/ktfv4F7PU5",
      {
        "neg": 0.039,
        "neu": 0.854,
        "pos": 0.107,
        "compound": 0.4448
      }
    ],
    [
      "When will you be getting more shorts in?",
      {
        "neg": 0.0,
        "neu": 1.0,
        "pos": 0.0,
        "compound": 0.0
      }
    ],
    [
      "I forgot you and drose relate on a personal level.",
      {
        "neg": 0.0,
        "neu": 1.0,
        "pos": 0.0,
        "compound": 0.0
      }
    ],
    [
      "Hence @ drose only needs to remain the starting POINT GUARD so he can continue being DRose... ...then it's Conference Finals & MVP time. # AllEyesNorth # Timberwolves @ Timberwolves @ Twolves_PR",
      {
        "neg": 0.0,
        "neu": 1.0,
        "pos": 0.0,
        "compound": 0.0
      }
    ],
    [
      "Angas ni drose!! https://twitter.com/Timberwolves/status/1060576788533805057 \u2026",
      {
        "neg": 0.0,
        "neu": 1.0,
        "pos": 0.0,
        "compound": 0.0
      }
    ],
    [
      "Cold dude @ drose https://twitter.com/gifdsports/status/1060397048070049793 \u2026",
      {
        "neg": 0.0,
        "neu": 1.0,
        "pos": 0.0,
        "compound": 0.0
      }
    ],
    [
      "Drose drose drose drose drose https://twitter.com/gifdsports/status/1060397048070049793 \u2026",
      {
        "neg": 0.0,
        "neu": 1.0,
        "pos": 0.0,
        "compound": 0.0
      }
    ],
    [
      "Get your Derrick Rose Prince inspired Jersey and # BballCrazy band. # Drose # Twolves http://BballCrazy.com pic.twitter.com/5SCVAgBs6E",
      {
        "neg": 0.0,
        "neu": 0.802,
        "pos": 0.198,
        "compound": 0.4939
      }
    ],
    [
      "Bron tryna take drose powers https://twitter.com/reckless_mall/status/1060635926433554432 \u2026",
      {
        "neg": 0.0,
        "neu": 1.0,
        "pos": 0.0,
        "compound": 0.0
      }
    ],
    [
      "Ur crazy.... Wiggins",
      {
        "neg": 0.0,
        "neu": 1.0,
        "pos": 0.0,
        "compound": 0.0
      }
    ],
    [
      "Get your Derrick Rose Prince inspired Jersey and # BballCrazy band. # Drose # Twolves http://BballCrazy.com pic.twitter.com/oHn6y4tct8",
      {
        "neg": 0.0,
        "neu": 0.802,
        "pos": 0.198,
        "compound": 0.4939
      }
    ],
    [
      "Hardwood Classic @ drose ? In stock? pic.twitter.com/cXVDzbQPPD",
      {
        "neg": 0.0,
        "neu": 1.0,
        "pos": 0.0,
        "compound": 0.0
      }
    ],
    [
      "Drose going crazy because and only because harden babied him last playoffs",
      {
        "neg": 0.179,
        "neu": 0.821,
        "pos": 0.0,
        "compound": -0.34
      }
    ],
    [
      "We LOVE seeing you do shit like this @ drose https://twitter.com/BleacherReport/status/1060564822767616000 \u2026",
      {
        "neg": 0.2,
        "neu": 0.388,
        "pos": 0.412,
        "compound": 0.5904
      }
    ],
    [
      "And drose gona win MVP right ????",
      {
        "neg": 0.0,
        "neu": 0.558,
        "pos": 0.442,
        "compound": 0.6966
      }
    ],
    [
      "... ...\uadf8\ub7fc \uacc4\uc18d \uacc1\uc5d0 \uc788\uc744\uae4c. ...(\ub208\uc744 \uafb9 \uac10\uace4 \ud798\uacb9\uac8c \uc228\uc744 \ub0b4\uc26c\ub354\ub2c8) ...\uc2dc\uac04\uc774 \ud758\ub800\uc73c\ub2c8\uae4c... ...\uc5b4\uca4c\uba74 \uc815\ub9d0... \ubcc0\ud55c \uac78\uc9c0\ub3c4 \ubaa8\ub974\uc9c0. ... ...\uc194\uc9c1\ud558\uac8c \ub9d0\ud574\uc918\ub3c4 \uad1c\ucc2e\uc544. \uc2eb\ub2e4\uba74 \ubc14\uafc0\uac8c...(\ub208\uce58) ... ...\uadf8\uac74... \uc5ed\uc2dc... \uc2eb\uc73c\ub824\ub098... ... \uadf8\ub9cc\ub450\ub294 \uac8c...\uc88b\uc744\uae4c.(\uc190 \uaf3c\uc9c8)",
      {
        "neg": 0.0,
        "neu": 1.0,
        "pos": 0.0,
        "compound": 0.0
      }
    ],
    [
      "@ adidasUS can yall release these again @ drose i had them a while back. Great shoe pic.twitter.com/2U859DKBGO",
      {
        "neg": 0.0,
        "neu": 0.76,
        "pos": 0.24,
        "compound": 0.6249
      }
    ],
    [
      "You don\u2019t even have to be a wolves fan or NBA fan, being a sports fan and seeing DRose back playing the way he did before having all these injuries is amazing. You often see guys get plagued by injury and quit. This man is only getting re-started. Only love.",
      {
        "neg": 0.046,
        "neu": 0.678,
        "pos": 0.276,
        "compound": 0.9169
      }
    ],
    [
      "How about the shorts?",
      {
        "neg": 0.0,
        "neu": 1.0,
        "pos": 0.0,
        "compound": 0.0
      }
    ],
    [
      "@ drose https://twitter.com/BleacherReport/status/1060564822767616000 \u2026",
      {
        "neg": 0.0,
        "neu": 1.0,
        "pos": 0.0,
        "compound": 0.0
      }
    ],
    [
      "Anybody but Jokic was a customized jersey like really?",
      {
        "neg": 0.0,
        "neu": 0.683,
        "pos": 0.317,
        "compound": 0.5023
      }
    ],
    [
      "I can\u2019t wait til my dude Drose come home, sooner than you think",
      {
        "neg": 0.0,
        "neu": 1.0,
        "pos": 0.0,
        "compound": 0.0
      }
    ],
    [
      "@ drose I see you putting in work. You most definitely are making history. Much love. Never give up.",
      {
        "neg": 0.0,
        "neu": 0.676,
        "pos": 0.324,
        "compound": 0.8016
      }
    ],
    [
      "Quote @ stephenasmith \u201cLord have mercy @ drose is coming\u201d",
      {
        "neg": 0.0,
        "neu": 0.737,
        "pos": 0.263,
        "compound": 0.3612
      }
    ],
    [
      "Oh DRose is BACK back https://twitter.com/BrilliantDum_e/status/1060921677142384641 \u2026",
      {
        "neg": 0.0,
        "neu": 1.0,
        "pos": 0.0,
        "compound": 0.0
      }
    ],
    [
      "Hoop heads!!! We\u2019re back for all of YOU! and get some knowledge and humor dropped on your domes! # Celtics # NBA # NBATwitter # DRose # LakeShow # Duke # Zionhttps://twitter.com/RunningPointPod/status/1060885668006641664 \u2026",
      {
        "neg": 0.0,
        "neu": 0.88,
        "pos": 0.12,
        "compound": 0.5053
      }
    ],
    [
      "Lol why can\u2019t they just sell all of them?",
      {
        "neg": 0.0,
        "neu": 0.741,
        "pos": 0.259,
        "compound": 0.4215
      }
    ],
    [
      "At least you had options. I only had Jokic",
      {
        "neg": 0.0,
        "neu": 1.0,
        "pos": 0.0,
        "compound": 0.0
      }
    ],
    [
      "@ NBA2K @ Ronnie2K if ya don\u2019t change @ drose rating and give @ KlayThompson a headband I\u2019m switching to # NBALive # jk",
      {
        "neg": 0.0,
        "neu": 0.894,
        "pos": 0.106,
        "compound": 0.2263
      }
    ],
    [
      "its time to rise !! @ drose # TheReturnOfTheWOLFpic.twitter.com/SqOo4WY9Cm",
      {
        "neg": 0.0,
        "neu": 1.0,
        "pos": 0.0,
        "compound": 0.0
      }
    ],
    2018,
    14
  ]
}