{
  "gordonhayward": [
    [
      "how are you feeling ?! Hope you get well soon # gocelts",
      {
        "neg": 0.0,
        "neu": 0.541,
        "pos": 0.459,
        "compound": 0.6996
      }
    ],
    [
      "My job got Gordon Hayward jerseys, so it\u2019s not just kyrie jerseys now",
      {
        "neg": 0.0,
        "neu": 1.0,
        "pos": 0.0,
        "compound": 0.0
      }
    ],
    [
      "Andrew Wiggins is not better than Gordon Hayward lmao https://twitter.com/kotaleblanc/status/928745130831548416 \u2026",
      {
        "neg": 0.168,
        "neu": 0.559,
        "pos": 0.273,
        "compound": 0.3599
      }
    ],
    [
      "Gordon Hayward says encouragment from Kobe Bryant, other athletes fueling recovery http://www.nba.com/article/2017/11/09/gordon-hayward-kobe-bryant-helps-inspire-recovery-leg-injury/?rss=true&utm_source=dlvr.it&utm_medium=twitter \u2026pic.twitter.com/SD4h8fGeNs",
      {
        "neg": 0.0,
        "neu": 1.0,
        "pos": 0.0,
        "compound": 0.0
      }
    ],
    [
      "Yahoo! Sports - http://newzbots.me/?156GP9L - Here&aposs How Gordon Hayward Spent His First Celtics-Lakers Game With Boston",
      {
        "neg": 0.0,
        "neu": 1.0,
        "pos": 0.0,
        "compound": 0.0
      }
    ],
    [
      "Here's How Gordon Hayward Spent His First Celtics-Lakers Game With Boston. https://nesn.com/2017/11/heres-how-gordon-hayward-spent-his-first-celtics-lakers-game-with-boston/?src=rss \u2026",
      {
        "neg": 0.0,
        "neu": 1.0,
        "pos": 0.0,
        "compound": 0.0
      }
    ],
    [
      "He carried Gordon Hayward onto the plane! Players will do anything for him!",
      {
        "neg": 0.0,
        "neu": 1.0,
        "pos": 0.0,
        "compound": 0.0
      }
    ],
    [
      "@ JLin7 you've got a challenge from @ gordonhayward in League pic.twitter.com/hcCWnAOlkj",
      {
        "neg": 0.0,
        "neu": 0.86,
        "pos": 0.14,
        "compound": 0.0772
      }
    ],
    [
      "Led by Jeff Moore\u2019s 2 points, 3 rebounds, and 3 assists, Gordon Hayward\u2019s Ankle \u201cruns away\u201d with their first victory. \u201ci knew i would be a little rusty in my first game back, but i took my shot, and we came out on top. It\u2019s good to be back,\u201d said Moore after the game # MVPpic.twitter.com/OK9WbleoKC",
      {
        "neg": 0.0,
        "neu": 0.886,
        "pos": 0.114,
        "compound": 0.7227
      }
    ],
    [
      "Glad you did not tear up your knee.... it is an even longer rehab! You will be back soon!!",
      {
        "neg": 0.0,
        "neu": 0.823,
        "pos": 0.177,
        "compound": 0.5962
      }
    ],
    [
      "Swear i just Gordon Hayward my ankle",
      {
        "neg": 0.194,
        "neu": 0.806,
        "pos": 0.0,
        "compound": -0.0516
      }
    ],
    [
      "@ gordonhayward Can you change the settings so when you stream on twitch, it's saved it so people can watch it later? Just saw your video interview with @ RollingStone + @ glixel",
      {
        "neg": 0.0,
        "neu": 0.909,
        "pos": 0.091,
        "compound": 0.4215
      }
    ],
    [
      "Gordon Hayward says encouragment from Kobe Bryant, other athletes fueling recove.... Related Articles: http://bit.ly/2Aoummu",
      {
        "neg": 0.0,
        "neu": 1.0,
        "pos": 0.0,
        "compound": 0.0
      }
    ],
    [
      "Gordon Hayward says encouragment from Kobe Bryant, other athletes fueling recovery http://destyy.com/wrsWph pic.twitter.com/75CuSqpv2H",
      {
        "neg": 0.0,
        "neu": 1.0,
        "pos": 0.0,
        "compound": 0.0
      }
    ],
    [
      "The # Celtics may be down a couple starters (three, if you count Gordon Hayward) tomorrow against the # Hornets.https://twitter.com/SteveBHoop/status/928761216390123520 \u2026",
      {
        "neg": 0.0,
        "neu": 1.0,
        "pos": 0.0,
        "compound": 0.0
      }
    ],
    [
      "Gordon Hayward says encouragment from Kobe Bryant, other athletes fueling recovery http://dlvr.it/Q07m7D pic.twitter.com/xYb5vqjBZ0",
      {
        "neg": 0.0,
        "neu": 1.0,
        "pos": 0.0,
        "compound": 0.0
      }
    ],
    [
      "Celtics because we are the best team and the future champions @ celtics @ gordonhayward @ KyrieIrving @ Al_Horford @ FCHWPO @ dtheis10 and others https://twitter.com/NBA_Buckets/status/928738350885896192 \u2026",
      {
        "neg": 0.0,
        "neu": 0.703,
        "pos": 0.297,
        "compound": 0.8225
      }
    ],
    [
      "Gordon Hayward says encouragment from Kobe Bryant, other athletes fueling recovery http://dlvr.it/Q07kB2 pic.twitter.com/vyYWBoMVxy",
      {
        "neg": 0.0,
        "neu": 1.0,
        "pos": 0.0,
        "compound": 0.0
      }
    ],
    [
      "ICYMI: @ Scalabrine challenged @ gordonhayward to a chair shooting competition\u2026 can you guess who won? http://bit.ly/2iGAsHD",
      {
        "neg": 0.082,
        "neu": 0.702,
        "pos": 0.216,
        "compound": 0.5106
      }
    ],
    [
      "I liked a @ YouTube video http://youtu.be/2JPJxLyXxvk?a How I Play: Boston Celtics' Gordon Hayward",
      {
        "neg": 0.0,
        "neu": 0.606,
        "pos": 0.394,
        "compound": 0.6369
      }
    ],
    [
      "Gordon Hayward sits down with Paul Pierce to discuss injury, rehabilitation | NBA Countdown | ESPN # GetWellGordon # Celtics https://www.youtube.com/watch?v=Sml0_a2q6Ds&sns=tw \u2026",
      {
        "neg": 0.149,
        "neu": 0.851,
        "pos": 0.0,
        "compound": -0.4215
      }
    ],
    [
      "Meanwhile @ gordonhayward thinking \u201cif I was on the court, I\u2019d be doing the same exact thing I\u2019m doing now, just watching Kyrie\u201d",
      {
        "neg": 0.0,
        "neu": 1.0,
        "pos": 0.0,
        "compound": 0.0
      }
    ],
    [
      "Seriously man?",
      {
        "neg": 0.63,
        "neu": 0.37,
        "pos": 0.0,
        "compound": -0.1779
      }
    ],
    [
      "Take every day as a little test. I think you'll find you're at your best. When you take each challenge in your stride. Because you have that Celtics pride. @ gordonhayward get it young king",
      {
        "neg": 0.0,
        "neu": 0.786,
        "pos": 0.214,
        "compound": 0.7845
      }
    ],
    [
      "Cant wait to see you",
      {
        "neg": 0.0,
        "neu": 1.0,
        "pos": 0.0,
        "compound": 0.0
      }
    ],
    [
      "Hey @ danielrainge I found your replacement for @ gordonhayward! https://twitter.com/govchrissununu/status/928739008322199552 \u2026",
      {
        "neg": 0.0,
        "neu": 1.0,
        "pos": 0.0,
        "compound": 0.0
      }
    ],
    [
      "Now that I have 280 characters. I\u2019d love to explain why this tweet sucks. 1) He really wasn\u2019t involved w the NCAA that long.. 2) he\u2019s been in the NBA twice as long as he was at LSU..probably wasn\u2019t done w core. 3) ITS THE NBA. I\u2019m sure Gordon Hayward learned more at Butler? No. https://twitter.com/bleacherreport/status/928746454524612608 \u2026",
      {
        "neg": 0.082,
        "neu": 0.81,
        "pos": 0.108,
        "compound": 0.3687
      }
    ],
    [
      "Bron better worry about Gordon Hayward coming back",
      {
        "neg": 0.246,
        "neu": 0.508,
        "pos": 0.246,
        "compound": 0.0
      }
    ],
    [
      "Jaylen Brown and Jayson Tatum step up as Boston Celtics lead the way without Gordon Hayward... Check out # theNBAscore by @ jamesbenge https://trib.al/zzhWzfg",
      {
        "neg": 0.0,
        "neu": 1.0,
        "pos": 0.0,
        "compound": 0.0
      }
    ],
    [
      "Je me demande ce qu'aurait donn\u00e9 les Celtics si Gordon Hayward ne s'\u00e9tait pas fracass\u00e9 la jambe... # NBA",
      {
        "neg": 0.0,
        "neu": 1.0,
        "pos": 0.0,
        "compound": 0.0
      }
    ],
    [
      "But every Celtics fan with a brain in their head knows that's a blow out (Barring a KD or Steph injury AND a healthy Gordon Hayward)",
      {
        "neg": 0.127,
        "neu": 0.651,
        "pos": 0.223,
        "compound": 0.4215
      }
    ],
    [
      "Come back stronger, better. Its a set back, but you can be even better than you were before, im confident in that. # Celtics life",
      {
        "neg": 0.0,
        "neu": 0.615,
        "pos": 0.385,
        "compound": 0.8979
      }
    ],
    [
      "Gordon don't worry you'll be out there soon!",
      {
        "neg": 0.0,
        "neu": 0.722,
        "pos": 0.278,
        "compound": 0.4015
      }
    ],
    [
      "@ JLin7 Do you accept @ gordonhayward challenge to play him in league of legends",
      {
        "neg": 0.0,
        "neu": 0.613,
        "pos": 0.387,
        "compound": 0.6486
      }
    ],
    [
      "\u03c4\u03af\u03c4\u03bb\u03bf\u03c2 \u03b5\u03bb\u03bb\u03b7\u03bd\u03b9\u03ba\u03bf\u03cd \u03c3\u03ac\u03b9\u03c4 Gordon Hayward: ''Can't wait to be a part of the Lakers...'' https://twitter.com/gordonhayward/status/928445481914683392 \u2026",
      {
        "neg": 0.0,
        "neu": 1.0,
        "pos": 0.0,
        "compound": 0.0
      }
    ],
    [
      "With all the talk about Lonzo struggling, it still doesn't take away from the fact that Gordon Hayward is afraid of playing against Lonzo. https://twitter.com/MastaRedSnappa/status/928415886372872193 \u2026",
      {
        "neg": 0.101,
        "neu": 0.833,
        "pos": 0.065,
        "compound": -0.25
      }
    ],
    [
      "Ha! I'm with you. I don't think I realized before this summer how important media/spotlight/national TV games/adulation was to him.",
      {
        "neg": 0.0,
        "neu": 0.781,
        "pos": 0.219,
        "compound": 0.5411
      }
    ],
    [
      "I wish Gordon Hayward was playing this year shit would be much easier for Kyrie Irving",
      {
        "neg": 0.164,
        "neu": 0.502,
        "pos": 0.333,
        "compound": 0.4019
      }
    ],
    [
      "Kyrie was traded... KD a free agent. And Kyrie also joined star such as Jaylen Brown, Gordon Hayward, and Al Horford. Bad take",
      {
        "neg": 0.131,
        "neu": 0.746,
        "pos": 0.123,
        "compound": -0.0516
      }
    ],
    [
      "Don't you remember Kyrie saying that there are no small things in life? Which is kind of true. He is too woke",
      {
        "neg": 0.089,
        "neu": 0.809,
        "pos": 0.101,
        "compound": 0.079
      }
    ],
    [
      "I just love @ gordonhayward. Wishing you a speedy recovery brother and the gaming community loves you dearly. I just ask for Banner 18 when you're back https://youtu.be/2JPJxLyXxvk",
      {
        "neg": 0.0,
        "neu": 0.613,
        "pos": 0.387,
        "compound": 0.9118
      }
    ],
    [
      "Get well soon legend",
      {
        "neg": 0.0,
        "neu": 0.588,
        "pos": 0.412,
        "compound": 0.2732
      }
    ],
    [
      "Gordon Hayward says encouragment from Kobe Bryant, other athletes fueling recovery http://dlvr.it/Q0753z",
      {
        "neg": 0.0,
        "neu": 1.0,
        "pos": 0.0,
        "compound": 0.0
      }
    ],
    [
      "I liked a @ YouTube video http://youtu.be/Sml0_a2q6Ds?a Gordon Hayward sits down with Paul Pierce to discuss injury, rehabilitation | NBA",
      {
        "neg": 0.143,
        "neu": 0.714,
        "pos": 0.143,
        "compound": 0.0
      }
    ],
    [
      "How dumb are the videos of @ gordonhayward shooting in a chair? I get why he went to Boston now. Only in a big market would like that be newsworthy. # notbitter # ipromise",
      {
        "neg": 0.104,
        "neu": 0.818,
        "pos": 0.079,
        "compound": -0.2023
      }
    ],
    [
      "Back to Basketball http://www.gordonhayward20.life/2017/09/21/back-to-basketball/ \u2026 \u0441 \u043f\u043e\u043c\u043e\u0449\u044c\u044e @ gordonhayward",
      {
        "neg": 0.0,
        "neu": 1.0,
        "pos": 0.0,
        "compound": 0.0
      }
    ],
    [
      "I liked a @ YouTube video http://youtu.be/2JPJxLyXxvk?a How I Play: Boston Celtics' Gordon Hayward",
      {
        "neg": 0.0,
        "neu": 0.606,
        "pos": 0.394,
        "compound": 0.6369
      }
    ],
    [
      "Get well my friend!! Can\u2019t wait for you to be totally healthy Gordon. It\u2019s gong to fun the next few years!!!!!",
      {
        "neg": 0.0,
        "neu": 0.571,
        "pos": 0.429,
        "compound": 0.9146
      }
    ],
    [
      "Gordon Hayward Explains To Paul Pierce How Kobe Bryant Has Helped In Recovery https://nesn.com/2017/11/gordon-hayward-explains-to-paul-pierce-how-kobe-bryant-has-helped-in-recovery/ \u2026pic.twitter.com/lutAI6QGkZ",
      {
        "neg": 0.0,
        "neu": 1.0,
        "pos": 0.0,
        "compound": 0.0
      }
    ],
    [
      "Gordon Hayward dropped the first game of the season and the Cavs have players that are healthy. Y\u2019all just . I bet if they was 10-0 you\u2019d be talking that not even saying it\u2019s just ten games in",
      {
        "neg": 0.0,
        "neu": 0.928,
        "pos": 0.072,
        "compound": 0.4019
      }
    ],
    [
      "@ gordonhayward get ready https://twitter.com/sportscenter/status/928436498537566208 \u2026",
      {
        "neg": 0.0,
        "neu": 0.545,
        "pos": 0.455,
        "compound": 0.3612
      }
    ],
    [
      "Yeah how is that moving good? Lol Gordon hayward could prob do that right now",
      {
        "neg": 0.0,
        "neu": 0.603,
        "pos": 0.397,
        "compound": 0.7845
      }
    ],
    [
      "Road to Recovery - Gordon Hayward Ready for Long Road Back from Devastating Injury # nba # celtics http://ballnroll.com/2017/11/road-to-recovery/ \u2026",
      {
        "neg": 0.314,
        "neu": 0.575,
        "pos": 0.111,
        "compound": -0.6808
      }
    ],
    [
      "Gordon Hayward sits down with Paul Pierce to discuss injury, rehabilitat... https://youtu.be/Sml0_a2q6Ds via @ YouTube",
      {
        "neg": 0.177,
        "neu": 0.823,
        "pos": 0.0,
        "compound": -0.4215
      }
    ],
    [
      "omg so fucked up",
      {
        "neg": 0.61,
        "neu": 0.39,
        "pos": 0.0,
        "compound": -0.6901
      }
    ],
    [
      "@ gordonhayward vs @ JLin7 .... hosted on the @ TheRealRyanHiga show",
      {
        "neg": 0.0,
        "neu": 1.0,
        "pos": 0.0,
        "compound": 0.0
      }
    ],
    [
      "Damn if Gordon Hayward ain\u2019t get hurt Eastern Conference playoffs would\u2019ve finally been lit",
      {
        "neg": 0.337,
        "neu": 0.663,
        "pos": 0.0,
        "compound": -0.7269
      }
    ],
    [
      "I don\u2019t know what\u2019s more painful to watch.... Gordon Hayward breaking his leg or missing the half court shot against Duke in the final game. Oh, and was that actually 7 years ago?!",
      {
        "neg": 0.164,
        "neu": 0.836,
        "pos": 0.0,
        "compound": -0.6893
      }
    ],
    [
      "I love how people can\u2019t say anything bad about the Celtics, so they just add a picture of Gordon Hayward or some Kyrie meme",
      {
        "neg": 0.126,
        "neu": 0.722,
        "pos": 0.152,
        "compound": 0.1779
      }
    ],
    [
      "Gordon Hayward injury is awful dreadful. But the youngsters are balling seemingly for their lives. Wow. https://twitter.com/celtics/status/928463635399180289 \u2026",
      {
        "neg": 0.243,
        "neu": 0.541,
        "pos": 0.216,
        "compound": 0.3291
      }
    ],
    [
      "Pour les fans du ... @ UtahJazz_France et @ celticsfr ... Cette carte d\u00e9dicac\u00e9e par @ gordonhayward ! 12\u20ac livraison incluse ! Contact en MP ! pic.twitter.com/fYsjlCYCFk",
      {
        "neg": 0.0,
        "neu": 1.0,
        "pos": 0.0,
        "compound": 0.0
      }
    ],
    [
      "Gordon Hayward is gone from Utah, so Rudy has taken up his mantle of saying \"like I said\" at least once or twice every interview. That's leadership. https://twitter.com/kylegoon/status/928714496411033600 \u2026",
      {
        "neg": 0.0,
        "neu": 0.912,
        "pos": 0.088,
        "compound": 0.3612
      }
    ],
    [
      "Can\u2019t wait to BOO the hell out of you!!",
      {
        "neg": 0.393,
        "neu": 0.607,
        "pos": 0.0,
        "compound": -0.7339
      }
    ],
    [
      "Wish you luck",
      {
        "neg": 0.0,
        "neu": 0.149,
        "pos": 0.851,
        "compound": 0.6908
      }
    ],
    [
      "Jag gillade en video p\u00e5 @ YouTube http://youtu.be/2JPJxLyXxvk?a How I Play: Boston Celtics' Gordon Hayward",
      {
        "neg": 0.0,
        "neu": 0.833,
        "pos": 0.167,
        "compound": 0.34
      }
    ],
    [
      "Now imagine if we could turn injuries off and @ gordonhayward was back on the court https://twitter.com/nba/status/928676069112102912 \u2026",
      {
        "neg": 0.0,
        "neu": 1.0,
        "pos": 0.0,
        "compound": 0.0
      }
    ],
    [
      "I don't think all three of us have ever cringed through a story like the Gordon Hayward story Kevin Harlan told! You have to hear it from a guy who was 50 feet away. https://twitter.com/XTRA1360/status/928692567528443904 \u2026",
      {
        "neg": 0.0,
        "neu": 0.917,
        "pos": 0.083,
        "compound": 0.4199
      }
    ],
    [
      ". @ gordonhayward sat down with Paul Pierce and @ ESPNNBA to discuss his injury and rehabilitation # PSEpr http://bit.ly/2AvGvXx",
      {
        "neg": 0.157,
        "neu": 0.843,
        "pos": 0.0,
        "compound": -0.4215
      }
    ],
    [
      "Could/Should have used a better headline. \u201cFinding a silver lining to Gordon Hayward\u2019s injury.\u201d https://twitter.com/the94feetreport/status/928630390754910208 \u2026",
      {
        "neg": 0.0,
        "neu": 0.805,
        "pos": 0.195,
        "compound": 0.4404
      }
    ],
    [
      "I don\u2019t get why people are rushing to say Lonzo shitty. What was Gordon Hayward stats his freshman year again? What about Jaylen Brown ? Give Lonzo a year in the league sheesh",
      {
        "neg": 0.12,
        "neu": 0.88,
        "pos": 0.0,
        "compound": -0.6072
      }
    ],
    [
      "Hang in there dude! You\u2019ll get back there!",
      {
        "neg": 0.0,
        "neu": 1.0,
        "pos": 0.0,
        "compound": 0.0
      }
    ],
    [
      "The Boston Celtics have won 10 straight games after starting 0-2 and the devastating injury to Gordon Hayward. They beat the Lakers last night without Horford. Kyrie Irving is the real deal ! The young players - Tatum and Brown are stepping up.",
      {
        "neg": 0.148,
        "neu": 0.74,
        "pos": 0.112,
        "compound": -0.4199
      }
    ],
    [
      "# Celtics # BostonCeltics # CelticsTalk Here's How Gordon Hayward Spent His First Celtics-Lakers Game With Boston http://dld.bz/gsRfB",
      {
        "neg": 0.0,
        "neu": 1.0,
        "pos": 0.0,
        "compound": 0.0
      }
    ],
    [
      "The Celtics are rolling right now. Imagine the damage they could be doing with Gordon Hayward. # Celtics # NBA # BUMKT3330https://twitter.com/BR_NBA/status/928464339425574913 \u2026",
      {
        "neg": 0.151,
        "neu": 0.849,
        "pos": 0.0,
        "compound": -0.4939
      }
    ],
    [
      "I liked a @ YouTube video http://youtu.be/2JPJxLyXxvk?a How I Play: Boston Celtics' Gordon Hayward",
      {
        "neg": 0.0,
        "neu": 0.606,
        "pos": 0.394,
        "compound": 0.6369
      }
    ],
    [
      "Guys evaluating Celtics got it wrong, cd win East this year and give West a run for their money because vets and rookies r happy! Put an overrated Gordon Hayward in mix and guys start bitching!\" Fuck him what about me\"! Watch!!!",
      {
        "neg": 0.129,
        "neu": 0.702,
        "pos": 0.169,
        "compound": 0.471
      }
    ],
    [
      "Gordon Hayward\u2019s point average this NBA season",
      {
        "neg": 0.0,
        "neu": 1.0,
        "pos": 0.0,
        "compound": 0.0
      }
    ],
    [
      "Wait so Gordon Hayward has been walking around in a walking boot right? Does this mean we have to warn Woody there\u2019s a snake in a boot?",
      {
        "neg": 0.071,
        "neu": 0.929,
        "pos": 0.0,
        "compound": -0.1926
      }
    ],
    [
      "I wonder how the cavs are doing currently",
      {
        "neg": 0.0,
        "neu": 1.0,
        "pos": 0.0,
        "compound": 0.0
      }
    ],
    [
      "Heck, while I'm at it... @ gordonhayward @ smart_MS3 @ jaytatum0 @ MookMorris2 @ aronbaynes @ AbdelNader2 @ dtheis10 @ semi @ jabari @ celticsblog @ CLNS_Nick",
      {
        "neg": 0.0,
        "neu": 1.0,
        "pos": 0.0,
        "compound": 0.0
      }
    ],
    [
      "@ gordonhayward hey big head we miss you.",
      {
        "neg": 0.211,
        "neu": 0.789,
        "pos": 0.0,
        "compound": -0.1531
      }
    ],
    [
      "Gordon Hayward deserves to be an all star # nbavote",
      {
        "neg": 0.0,
        "neu": 1.0,
        "pos": 0.0,
        "compound": 0.0
      }
    ],
    [
      "I liked a @ YouTube video http://youtu.be/Sml0_a2q6Ds?a Gordon Hayward sits down with Paul Pierce to discuss injury, rehabilitation | NBA",
      {
        "neg": 0.143,
        "neu": 0.714,
        "pos": 0.143,
        "compound": 0.0
      }
    ],
    [
      "i would like to formally announce that after 8 years of retirement, i\u2019ve decided to chase after my dreams once again. In 3 short hours, i will be suiting up and balling out for the 1st time since middle school. Come support Gordon Hayward\u2019s Ankle @Ramsey at 5 o clock # Ballislife",
      {
        "neg": 0.0,
        "neu": 0.842,
        "pos": 0.158,
        "compound": 0.7845
      }
    ],
    [
      "Blessing In Disguise! How @ jaytatum0 & @ FCHWPO are stepping to the plate after losing @ gordonhayward. https://94feetreport.com/gordon-haywards-injury-a-blessing-in-disguise-d9804229e5c1 \u2026",
      {
        "neg": 0.243,
        "neu": 0.597,
        "pos": 0.159,
        "compound": -0.1759
      }
    ],
    [
      "And yeah i love @ gordonhayward even more!!! # MyGuy! # Gamer # BleedGreen https://youtu.be/2JPJxLyXxvk",
      {
        "neg": 0.0,
        "neu": 0.514,
        "pos": 0.486,
        "compound": 0.8209
      }
    ],
    [
      "You're doing a great duty greenie # smallthings",
      {
        "neg": 0.0,
        "neu": 0.549,
        "pos": 0.451,
        "compound": 0.6249
      }
    ],
    [
      "Gordon Hayward Reveals How Kobe Bryant Has Been Helping in His Recovery http://ow.ly/t9Nw50f5rpy",
      {
        "neg": 0.0,
        "neu": 0.845,
        "pos": 0.155,
        "compound": 0.296
      }
    ],
    [
      "Celtics lost Gordon Hayward and went on a 10 game win streak. Swear no media and hot take outlet saw that coming",
      {
        "neg": 0.215,
        "neu": 0.642,
        "pos": 0.143,
        "compound": 0.0258
      }
    ],
    [
      "Kobe Bryant's # Instagram Message to Gordon Hayward Teaches a Powerful Lesson in Emotional Intelligence https://buff.ly/2gJIFhl / # sports",
      {
        "neg": 0.0,
        "neu": 0.615,
        "pos": 0.385,
        "compound": 0.7579
      }
    ],
    [
      "I agree with you bud celtics are good but we both got two different opinions my man i wish he was healthy to see him battle in the playoffs tho",
      {
        "neg": 0.091,
        "neu": 0.618,
        "pos": 0.29,
        "compound": 0.7506
      }
    ],
    [
      "How do they not matchup against the celtics just read that? Gosh I hope you are just being biased lol",
      {
        "neg": 0.088,
        "neu": 0.672,
        "pos": 0.239,
        "compound": 0.5574
      }
    ],
    [
      "The celtics are hot tho playing good basketball",
      {
        "neg": 0.0,
        "neu": 0.561,
        "pos": 0.439,
        "compound": 0.5719
      }
    ],
    [
      "With Eric Bledsoe and when Jabari gets back they are gonna challenge the cavs",
      {
        "neg": 0.0,
        "neu": 0.909,
        "pos": 0.091,
        "compound": 0.0772
      }
    ],
    [
      "If Gordon Hayward doesn\u2019t get injured....Dare I say it I think the Celtics would be undefeated right now",
      {
        "neg": 0.0,
        "neu": 1.0,
        "pos": 0.0,
        "compound": 0.0
      }
    ],
    [
      "ICYMI: @hardwina and @ Judson1360 had a great lineup of guests today including: @ Kevinharlan @ JamesPalmerTV @ alexmarvez @ Aztec_MBB HC Brian Dutcher Kevin Harlan talking about witnessing Gordon Hayward's injury is a must listen! https://1360sports.iheart.com/featured/hardwick-and-richards/content/2017-11-09-119-interviews-kevin-harlan-james-palmer-alex-marvez-and-coach-dutcher/ \u2026",
      {
        "neg": 0.08,
        "neu": 0.796,
        "pos": 0.125,
        "compound": 0.3802
      }
    ],
    [
      "Good stuff @ paulpierce34. One luv bro. @ gordonhayward, continue to gws brutha. One luv... # CelticsUp # Celticshttps://twitter.com/BostonDotCom/status/928434074024325120 \u2026",
      {
        "neg": 0.0,
        "neu": 0.828,
        "pos": 0.172,
        "compound": 0.4404
      }
    ],
    [
      "As long as we winning idc what that nigga say. Niggas real lucky we don't got Gordon Hayward",
      {
        "neg": 0.102,
        "neu": 0.636,
        "pos": 0.263,
        "compound": 0.5859
      }
    ],
    [
      "The latest new from around the NBA follow us. Gordon Hayward says encouragment from Kobe Bryant, other athletes... http://ow.ly/lqvY50f5q2g",
      {
        "neg": 0.0,
        "neu": 1.0,
        "pos": 0.0,
        "compound": 0.0
      }
    ],
    [
      "Here's how Gordon Hayward spent his first Celtics-Lakers game since signing with Boston: http://nesn.com/?p=791150 pic.twitter.com/UqfOLPAbSo",
      {
        "neg": 0.0,
        "neu": 1.0,
        "pos": 0.0,
        "compound": 0.0
      }
    ],
    [
      "Gordon Hayward: \"A person that really has lifted me up and that I've been in touch with is Kobe. He sent that Instagram post, and he\u2019s emailed me a couple times too\" pic.twitter.com/oS27L15Zik",
      {
        "neg": 0.0,
        "neu": 1.0,
        "pos": 0.0,
        "compound": 0.0
      }
    ],
    [
      "Lol smh",
      {
        "neg": 0.451,
        "neu": 0.0,
        "pos": 0.549,
        "compound": 0.128
      }
    ],
    [
      "Gordon Hayward",
      {
        "neg": 0.0,
        "neu": 1.0,
        "pos": 0.0,
        "compound": 0.0
      }
    ],
    [
      "Your foot is going to smell when you take all of that off lol",
      {
        "neg": 0.0,
        "neu": 0.823,
        "pos": 0.177,
        "compound": 0.4215
      }
    ],
    [
      "The Celtics would\u2019ve been too Crazy wit Gordon Hayward",
      {
        "neg": 0.231,
        "neu": 0.769,
        "pos": 0.0,
        "compound": -0.34
      }
    ],
    [
      "If there's one thing I'm not getting enough of, it's updates on Gordon Hayward.",
      {
        "neg": 0.0,
        "neu": 1.0,
        "pos": 0.0,
        "compound": 0.0
      }
    ],
    [
      "Stay strong, Gordon! Your fellow Bulldogs have your back!",
      {
        "neg": 0.0,
        "neu": 0.673,
        "pos": 0.327,
        "compound": 0.5972
      }
    ],
    [
      "The Celtics doing what they doing now .. imagine if Gordon Hayward didn't get injured",
      {
        "neg": 0.0,
        "neu": 0.861,
        "pos": 0.139,
        "compound": 0.3089
      }
    ],
    [
      "Miss you love you come back.... or just come over",
      {
        "neg": 0.116,
        "neu": 0.58,
        "pos": 0.304,
        "compound": 0.5574
      }
    ],
    [
      ". @ gordonhayward When you get back, this team is going to the Finals.",
      {
        "neg": 0.0,
        "neu": 1.0,
        "pos": 0.0,
        "compound": 0.0
      }
    ],
    [
      "Gordon Hayward, I hope they take away his crutches and all of his 4th of Julys. https://twitter.com/JakeScottZone/status/928676951627198464 \u2026",
      {
        "neg": 0.0,
        "neu": 0.838,
        "pos": 0.162,
        "compound": 0.4404
      }
    ],
    [
      "",
      {
        "neg": 0.0,
        "neu": 0.0,
        "pos": 0.0,
        "compound": 0.0
      }
    ],
    [
      "I spoke with @ daanteee about everything from his recovery from shoulder surgery, his reaction to Gordon Hayward's injury, his relationship with Ben Simmons, the new Call of Duty and a lot more for @ FanSided. Check it out:https://fansided.com/2017/11/09/dante-exum-injury-recovery-ben-simmons-call-of-duty/ \u2026",
      {
        "neg": 0.076,
        "neu": 0.924,
        "pos": 0.0,
        "compound": -0.4215
      }
    ],
    [
      ". @ gordonhayward says encouragement from @ kobebryant, other athletes fueling recovery. MORE: http://on.nba.com/2hofMHQ pic.twitter.com/DFpM6mK1QO",
      {
        "neg": 0.0,
        "neu": 0.797,
        "pos": 0.203,
        "compound": 0.4215
      }
    ],
    [
      "NBA Newsfeed Gordon Hayward says encouragment from Kobe Bryant, other athletes fueling recovery http://ow.ly/Thkc50f5mYa",
      {
        "neg": 0.0,
        "neu": 1.0,
        "pos": 0.0,
        "compound": 0.0
      }
    ],
    [
      "@ gordonhayward let's duo in Overwatch sometime bro.",
      {
        "neg": 0.0,
        "neu": 1.0,
        "pos": 0.0,
        "compound": 0.0
      }
    ],
    [
      "On some real shit, the message Kobe Bryant sent to Gordon Hayward was insanely inspiring and motivating. I mean it happened a month ago, but still.",
      {
        "neg": 0.084,
        "neu": 0.769,
        "pos": 0.147,
        "compound": 0.1779
      }
    ],
    [
      "Chair shooting contest between @ gordonhayward and @ Scalabrine was surprising as white mamba struggled # Celtics http://www.nbcsports.com/boston/video/gordon-hayward-vs-brian-scalabrine-chair-shooting-championship \u2026",
      {
        "neg": 0.137,
        "neu": 0.743,
        "pos": 0.12,
        "compound": -0.0772
      }
    ],
    [
      "Celtics have thoroughly impressed me so far this season, loss of Gordon Hayward for the season has been minimized by Tatum and Brown. As for Kyrie hes the best player in the league rn if he keeps this up expect him to win MVP",
      {
        "neg": 0.043,
        "neu": 0.745,
        "pos": 0.212,
        "compound": 0.8777
      }
    ],
    [
      "How I Play Boston Celtics Gordon Hayward - http://americastube.com/video/999iu3ug9xik?how-i-play-boston-celtics-gordon-hayward \u2026",
      {
        "neg": 0.0,
        "neu": 0.714,
        "pos": 0.286,
        "compound": 0.34
      }
    ],
    [
      "Yes he is, what the fuck are you talking about?",
      {
        "neg": 0.246,
        "neu": 0.563,
        "pos": 0.19,
        "compound": -0.2023
      }
    ],
    [
      "Kobe Bryant has reportedly been helping Gordon Hayward during recovery via @ TheVertical",
      {
        "neg": 0.0,
        "neu": 0.833,
        "pos": 0.167,
        "compound": 0.296
      }
    ],
    [
      "@ gordonhayward is shooting with a broken ankle. Wow pic.twitter.com/XvyprLUz0W",
      {
        "neg": 0.24,
        "neu": 0.465,
        "pos": 0.295,
        "compound": 0.1779
      }
    ],
    [
      "@ gordonhayward @ whitemamba54 Awesome for sure poor some good ole smack talk too#you was good to watch to Scalhttps://twitter.com/NBCSBoston/status/928353487032930306 \u2026",
      {
        "neg": 0.11,
        "neu": 0.459,
        "pos": 0.431,
        "compound": 0.8442
      }
    ],
    [
      "Collector's Item # gordonhayward # NBApic.twitter.com/IXuyzj9W8b",
      {
        "neg": 0.0,
        "neu": 1.0,
        "pos": 0.0,
        "compound": 0.0
      }
    ],
    [
      "Before there was Gordon Hayward, there was Edgar Sosa, who can empathize, and sympathize. By @ scottcacciola: http://nyti.ms/2zpVZi6",
      {
        "neg": 0.0,
        "neu": 1.0,
        "pos": 0.0,
        "compound": 0.0
      }
    ],
    [
      "Gordon Hayward says encouragment from Kobe Bryant, other athletes fueling recovery http://www.nba.com/article/2017/11/09/gordon-hayward-kobe-bryant-helps-inspire-recovery-leg-injury/?rss=true \u2026",
      {
        "neg": 0.0,
        "neu": 1.0,
        "pos": 0.0,
        "compound": 0.0
      }
    ],
    [
      "# Celtics # BostonCeltics # CelticsTalk Gordon Hayward Explains To Paul Pierce How Kobe Bryant Has Helped In Reco.. http://dld.bz/gsQhp",
      {
        "neg": 0.0,
        "neu": 1.0,
        "pos": 0.0,
        "compound": 0.0
      }
    ],
    [
      "Go Jazz.",
      {
        "neg": 0.0,
        "neu": 1.0,
        "pos": 0.0,
        "compound": 0.0
      }
    ],
    [
      "You say the 04 pistons are@the best team ever. Not one of those players is top 10 at their positions! Bulls at least got 2 top 10 of all time at their position",
      {
        "neg": 0.0,
        "neu": 0.782,
        "pos": 0.218,
        "compound": 0.7959
      }
    ],
    [
      "We would love a visit from @ gordonhayward. We are HUGE Celtics fanS in southern RI. # 10inarowandcounting",
      {
        "neg": 0.0,
        "neu": 0.643,
        "pos": 0.357,
        "compound": 0.8038
      }
    ],
    [
      "You know I was riding with the Celtics last year to make the finals.",
      {
        "neg": 0.0,
        "neu": 1.0,
        "pos": 0.0,
        "compound": 0.0
      }
    ],
    [
      "Gordon Hayward Explains To Paul Pierce How Kobe Bryant Has Helped In Recovery https://nesn.com/2017/11/gordon-hayward-explains-to-paul-pierce-how-kobe-bryant-has-helped-in-recovery/ \u2026 via @ NESN",
      {
        "neg": 0.0,
        "neu": 1.0,
        "pos": 0.0,
        "compound": 0.0
      }
    ],
    [
      "Me siento Gordon Hayward en este momento",
      {
        "neg": 0.0,
        "neu": 1.0,
        "pos": 0.0,
        "compound": 0.0
      }
    ],
    [
      "the Crosset Eagles will touch your pic before every game to show appreciation just to be able to play!pic.twitter.com/zYKjYHxgoN",
      {
        "neg": 0.0,
        "neu": 0.834,
        "pos": 0.166,
        "compound": 0.5562
      }
    ],
    [
      "Get Well Soon Gordon Hayward # Celtics # nba # basketball # greatplayer I Hope You Back & Keep Strong",
      {
        "neg": 0.0,
        "neu": 0.57,
        "pos": 0.43,
        "compound": 0.8074
      }
    ],
    [
      "Gordon Hayward Explains To Paul Pierce How Kobe Bryant Has Helped In Recovery. https://nesn.com/2017/11/gordon-hayward-explains-to-paul-pierce-how-kobe-bryant-has-helped-in-recovery/?src=rss \u2026",
      {
        "neg": 0.0,
        "neu": 1.0,
        "pos": 0.0,
        "compound": 0.0
      }
    ],
    [
      "Gordon Hayward still got it! # Celtics (via @ bleacherreport)pic.twitter.com/HgRQbaVfkw",
      {
        "neg": 0.0,
        "neu": 1.0,
        "pos": 0.0,
        "compound": 0.0
      }
    ],
    [
      "@ gordonhayward just want you to know that you have a lot of people in Crossett Arkansas rooting for you pic.twitter.com/ZNUw6MhNjq",
      {
        "neg": 0.0,
        "neu": 0.933,
        "pos": 0.067,
        "compound": 0.0772
      }
    ],
    [
      "Yahoo! Sports - http://newzbots.me/?156GOV0 - Gordon Hayward Explains To Paul Pierce How Kobe Bryant Has Helped In Recovery",
      {
        "neg": 0.0,
        "neu": 1.0,
        "pos": 0.0,
        "compound": 0.0
      }
    ],
    [
      "Gordon Hayward says Kobe Bryant has been helping him in injury recovery. http://www.nydailynews.com/sports/basketball/gordon-hayward-kobe-bryant-keeping-motivated-article-1.3621691?src=rss \u2026",
      {
        "neg": 0.175,
        "neu": 0.688,
        "pos": 0.138,
        "compound": -0.1531
      }
    ],
    [
      "# BostonCeltics # Bryant # ClevelandCavaliers # Gordon # GordonHayward # Hayward # Keeping # KobeBryant # KyrieIrving # Motivated # Nba ...",
      {
        "neg": 0.0,
        "neu": 0.786,
        "pos": 0.214,
        "compound": 0.4588
      }
    ],
    [
      "Gordon Hayward Explains To Paul Pierce How Kobe Bryant Has Helped In Recovery http://ift.tt/2yKLdDN",
      {
        "neg": 0.0,
        "neu": 1.0,
        "pos": 0.0,
        "compound": 0.0
      }
    ],
    [
      "Kobe Bryant, mentor de Gordon Hayward, uno de los grandes apoyos en la recuperaci\u00f3n del alero. # Celtics # NBApic.twitter.com/Z1QptmGkvR",
      {
        "neg": 0.0,
        "neu": 1.0,
        "pos": 0.0,
        "compound": 0.0
      }
    ],
    [
      "You are in spirit G. If you dedicate to your rehab, like you do your for b-ball. You will be back before you know it! # CsUp",
      {
        "neg": 0.0,
        "neu": 0.842,
        "pos": 0.158,
        "compound": 0.5411
      }
    ],
    [
      ".gordonhayward says encouragment from kobebryant, other athletes fueling recovery MORE:\u2026 https://twitter.com/i/web/status/928668528785350656 \u2026",
      {
        "neg": 0.0,
        "neu": 1.0,
        "pos": 0.0,
        "compound": 0.0
      }
    ],
    [
      "Gordon Hayward says Kobe Bryant has been helping him in injury recovery http://ift.tt/2zvwOs1",
      {
        "neg": 0.175,
        "neu": 0.688,
        "pos": 0.138,
        "compound": -0.1531
      }
    ],
    [
      "Edgar Sosa had a similar injury to Gordon Hayward's. But he had to do his rehab at a YMCA. http://nyti.ms/2yK1E2Q",
      {
        "neg": 0.101,
        "neu": 0.899,
        "pos": 0.0,
        "compound": -0.2263
      }
    ],
    [
      "Paul Pierce checks in with Gordon Hayward on his road to recovery! # Celticspic.twitter.com/o9K3UVuutR",
      {
        "neg": 0.0,
        "neu": 1.0,
        "pos": 0.0,
        "compound": 0.0
      }
    ],
    [
      ". @ gordonhayward says encouragment from @ kobebryant, other athletes fueling recovery MORE: http://on.nba.com/2malChk pic.twitter.com/eYweqv1Edn",
      {
        "neg": 0.0,
        "neu": 1.0,
        "pos": 0.0,
        "compound": 0.0
      }
    ],
    [
      "Gordon Hayward says encouragment from Kobe Bryant, other athletes fueling recovery # sportshypnosis http://www.nba.com/article/2017/11/09/gordon-hayward-kobe-bryant-helps-inspire-recovery-leg-injury/?rss=true \u2026",
      {
        "neg": 0.0,
        "neu": 1.0,
        "pos": 0.0,
        "compound": 0.0
      }
    ],
    [
      "Still wouldn\u2019t get by the wizards,bucks, or cavs",
      {
        "neg": 0.0,
        "neu": 1.0,
        "pos": 0.0,
        "compound": 0.0
      }
    ],
    [
      "In an interview with Paul Pierce, Gordon Hayward explained how Kobe Bryant has helped in his recovery. http://nesn.com/?p=791114 pic.twitter.com/Cfoe4IW2xk",
      {
        "neg": 0.0,
        "neu": 1.0,
        "pos": 0.0,
        "compound": 0.0
      }
    ],
    [
      "Scal Is An Important Part Of The Celtics Chemistry. Humor, Honestly, and Has Fun Doing It. Hayward Tossing Jabs Shows His Spirits Are Up # celtics",
      {
        "neg": 0.0,
        "neu": 0.673,
        "pos": 0.327,
        "compound": 0.8481
      }
    ],
    [
      "You can thank @ KyrieIrving for that haha",
      {
        "neg": 0.0,
        "neu": 0.476,
        "pos": 0.524,
        "compound": 0.6705
      }
    ],
    [
      "When you are playing @ NBA2K and @ gordonhayward \u2018s injury heals for game 7 of the nba finals :OOOO",
      {
        "neg": 0.143,
        "neu": 0.765,
        "pos": 0.092,
        "compound": -0.25
      }
    ],
    [
      "Gordon Hayward says Kobe Bryant has been keeping him motivated http://nydn.us/2ynjtAN - @ brettbodnerpic.twitter.com/I7M9Z4IbZ7",
      {
        "neg": 0.0,
        "neu": 0.786,
        "pos": 0.214,
        "compound": 0.4588
      }
    ],
    [
      "Gordon Hayward says Kobe Bryant has been keeping him motivated http://nydn.us/2ykXYQU - @ brettbodnerpic.twitter.com/KyZXH5ES84",
      {
        "neg": 0.0,
        "neu": 0.786,
        "pos": 0.214,
        "compound": 0.4588
      }
    ],
    [
      "I liked a @ YouTube video http://youtu.be/qX5c0JghxQY?a Kevin Durant's Live Reaction To Gordon Hayward's Injury",
      {
        "neg": 0.179,
        "neu": 0.641,
        "pos": 0.179,
        "compound": 0.0
      }
    ],
    [
      "After Gordon Hayward-like injury, Wyoming's Conner Cain recovering from surgery https://buff.ly/2yjvIhw # gowyopic.twitter.com/mmx22QziOU",
      {
        "neg": 0.203,
        "neu": 0.797,
        "pos": 0.0,
        "compound": -0.4215
      }
    ],
    [
      "Love it",
      {
        "neg": 0.0,
        "neu": 0.192,
        "pos": 0.808,
        "compound": 0.6369
      }
    ],
    [
      "it's just occurred to me that the celtics are going all this without @ gordonhayward.....can you IMAGINE the damage they're gonna do with him",
      {
        "neg": 0.127,
        "neu": 0.873,
        "pos": 0.0,
        "compound": -0.4939
      }
    ],
    [
      "Gordon Hayward making shots sitting down while lonzo ball struggles to shoot from field",
      {
        "neg": 0.29,
        "neu": 0.71,
        "pos": 0.0,
        "compound": -0.5994
      }
    ],
    [
      "I'll easily get the 20 @ gordonhayward was getting",
      {
        "neg": 0.0,
        "neu": 0.745,
        "pos": 0.255,
        "compound": 0.34
      }
    ],
    [
      "Hey @ gordonhayward I know a small deserving school in Rhode Island that would love a visit from you # HopeValleyElementarySchool @ JoeGencarelli1",
      {
        "neg": 0.0,
        "neu": 0.792,
        "pos": 0.208,
        "compound": 0.6369
      }
    ],
    [
      "Thanks Fam",
      {
        "neg": 0.0,
        "neu": 0.256,
        "pos": 0.744,
        "compound": 0.4404
      }
    ],
    [
      "Gordon Hayward sits down with Paul Pierce to discuss injury, rehabilitat... https://www.youtube.com/watch?v=Sml0_a2q6Ds&feature=share \u2026",
      {
        "neg": 0.203,
        "neu": 0.797,
        "pos": 0.0,
        "compound": -0.4215
      }
    ],
    [
      "Charles Barkley after Gordon Hayward injury m - \u201c Celtics are finished, there definitely not better than the cavs, bucks, Wizards, heat\u201d this guy gets paid to get roasted by shaq that\u2019s it. Basketball input absolutely awful",
      {
        "neg": 0.206,
        "neu": 0.728,
        "pos": 0.066,
        "compound": -0.7003
      }
    ],
    [
      "Gordon Hayward says Kobe Bryant has been keeping him motivated http://nydn.us/2zveLEz",
      {
        "neg": 0.0,
        "neu": 0.769,
        "pos": 0.231,
        "compound": 0.4588
      }
    ],
    [
      "Top story: Gordon Hayward says encouragment from Kobe Bryant, other athletes fu\u2026 http://www.nba.com/article/2017/11/09/gordon-hayward-kobe-bryant-helps-inspire-recovery-leg-injury/?rss=true \u2026, see more http://tweetedtimes.com/ProfiletreeBN?s=tnp \u2026",
      {
        "neg": 0.0,
        "neu": 0.881,
        "pos": 0.119,
        "compound": 0.2869
      }
    ],
    [
      "Gordon Hayward broke his leg # MakeMeAngryIn5Words",
      {
        "neg": 0.359,
        "neu": 0.641,
        "pos": 0.0,
        "compound": -0.4215
      }
    ],
    [
      "Celtics on a 10 game win streak, it's awesome but bittersweet, wish we had @ gordonhayward out on the court!",
      {
        "neg": 0.06,
        "neu": 0.578,
        "pos": 0.363,
        "compound": 0.8096
      }
    ],
    [
      "It\u2019s like your fav player going to a different team. Still going to support your fav player right?",
      {
        "neg": 0.0,
        "neu": 0.537,
        "pos": 0.463,
        "compound": 0.8807
      }
    ],
    [
      "Gordon Hayward says encouragment from Kobe Bryant, other athletes fueling recovery http://www.nba.com/article/2017/11/09/gordon-hayward-kobe-bryant-helps-inspire-recovery-leg-injury/?rss=true&utm_source=dlvr.it&utm_medium=twitter \u2026pic.twitter.com/CHuztSyw20",
      {
        "neg": 0.0,
        "neu": 1.0,
        "pos": 0.0,
        "compound": 0.0
      }
    ],
    [
      "Get the Gordon Hayward cut",
      {
        "neg": 0.344,
        "neu": 0.656,
        "pos": 0.0,
        "compound": -0.2732
      }
    ],
    [
      "I wanna have a crutch lunch with @ gordonhayward ... @ celtics # NBA # celtics # boston # footproblemshttps://twitter.com/1025marissa/status/928653845374357504 \u2026",
      {
        "neg": 0.0,
        "neu": 1.0,
        "pos": 0.0,
        "compound": 0.0
      }
    ],
    [
      "Who would have thought the @ celtics would still dominate without @ gordonhayward ? http://es.pn/2hVH19D",
      {
        "neg": 0.12,
        "neu": 0.88,
        "pos": 0.0,
        "compound": -0.128
      }
    ],
    [
      "So cool to see @ KyrieIrving Do his thang, w/ the @ celtics w/ No Drama/DramaQueen. Building from the Ground Up on his own, even Losing @ gordonhayward and still winning 10 Str8! How lethal they are now,so young,when Hayward gets back? # DamSon!",
      {
        "neg": 0.101,
        "neu": 0.76,
        "pos": 0.139,
        "compound": 0.417
      }
    ],
    [
      "Ready to do these for horford and Tatum?",
      {
        "neg": 0.0,
        "neu": 0.737,
        "pos": 0.263,
        "compound": 0.3612
      }
    ],
    [
      "Starting to think the @ celtics don't need @ gordonhayward.",
      {
        "neg": 0.0,
        "neu": 1.0,
        "pos": 0.0,
        "compound": 0.0
      }
    ],
    [
      "\u65e9\u304f\u5e30\u3063\u3066\u304d\u3066\u304f\u308c\uff01\uff01",
      {
        "neg": 0.0,
        "neu": 1.0,
        "pos": 0.0,
        "compound": 0.0
      }
    ],
    [
      "Nah, he was supporting Hayward last year on the jazz",
      {
        "neg": 0.114,
        "neu": 0.65,
        "pos": 0.236,
        "compound": 0.3612
      }
    ],
    [
      "That\u2019s the goal",
      {
        "neg": 0.0,
        "neu": 1.0,
        "pos": 0.0,
        "compound": 0.0
      }
    ],
    [
      "Lots and lots of prayers for a quick recovery!",
      {
        "neg": 0.0,
        "neu": 1.0,
        "pos": 0.0,
        "compound": 0.0
      }
    ],
    [
      "\"I thought my career was over.\" Maimed but undefeated, a basketball player knows the hard road Gordon Hayward faces. http://nyti.ms/2hgntfm pic.twitter.com/8xQ9CD4MdC",
      {
        "neg": 0.078,
        "neu": 0.922,
        "pos": 0.0,
        "compound": -0.1531
      }
    ],
    [
      "wait you forget Al Horford and Gordon Hayward",
      {
        "neg": 0.213,
        "neu": 0.787,
        "pos": 0.0,
        "compound": -0.2263
      }
    ],
    [
      "Imagine Kyrie, Jaylen, and Tatum WITH Gordon Hayward a year or two from now - could be downright scary",
      {
        "neg": 0.167,
        "neu": 0.833,
        "pos": 0.0,
        "compound": -0.4939
      }
    ],
    [
      "Maimed but Unbowed, He Understands What Lies Ahead for Gordon Hayward ( @ ScottCacciola - @ nytimes) https://redef.it/2AnZPFh",
      {
        "neg": 0.222,
        "neu": 0.778,
        "pos": 0.0,
        "compound": -0.5719
      }
    ],
    [
      "Is it possible for sports center to talk about the Celtics without mentioning the Gordon Hayward injury??",
      {
        "neg": 0.165,
        "neu": 0.835,
        "pos": 0.0,
        "compound": -0.4871
      }
    ],
    [
      "I\u2019m not a Celtics fan but damn I wish Gordon Hayward didn\u2019t get injured",
      {
        "neg": 0.426,
        "neu": 0.397,
        "pos": 0.176,
        "compound": -0.6163
      }
    ],
    [
      "NBA Boston Celtics Player Gordon Hayward Opens Up About His Devastating ... https://youtu.be/Z12u7TqzsO0 via @ YouTube",
      {
        "neg": 0.235,
        "neu": 0.765,
        "pos": 0.0,
        "compound": -0.6486
      }
    ],
    [
      "Gordon it's all a matter of time. I'm missing the No 20 jersey of the celtics on the court.",
      {
        "neg": 0.215,
        "neu": 0.732,
        "pos": 0.054,
        "compound": -0.5106
      }
    ],
    [
      "Maimed but Unbowed, He Understands What Lies Ahead for Gordon Hayward https://nyti.ms/2jcHeJ4",
      {
        "neg": 0.252,
        "neu": 0.748,
        "pos": 0.0,
        "compound": -0.5719
      }
    ],
    [
      "@ Ryan_Potvin it\u2019s just a chance for him to improve his @ PlayOverwatch skills",
      {
        "neg": 0.0,
        "neu": 0.647,
        "pos": 0.353,
        "compound": 0.5994
      }
    ],
    [
      "My squad 10-2 keep \u2018em coming!! # BostonCeltics # GordonWeMissYou @ KyrieIrving @ celtics @ gordonhayward",
      {
        "neg": 0.0,
        "neu": 1.0,
        "pos": 0.0,
        "compound": 0.0
      }
    ],
    [
      "Gordon Hayward desde la mitad de la cancha. Ojal\u00e1 se recupere y vuelva muy pronto !!! pic.twitter.com/5MFhsK7wkl",
      {
        "neg": 0.0,
        "neu": 1.0,
        "pos": 0.0,
        "compound": 0.0
      }
    ],
    [
      "That's supposed to be funny right?",
      {
        "neg": 0.0,
        "neu": 0.633,
        "pos": 0.367,
        "compound": 0.4404
      }
    ],
    [
      "How I Play Boston Celtics Gordon Hayward - http://americastube.com/video/999iu3ug9xik?how-i-play-boston-celtics-gordon-hayward \u2026",
      {
        "neg": 0.0,
        "neu": 0.714,
        "pos": 0.286,
        "compound": 0.34
      }
    ],
    [
      "Wonder if Felger thinks Gordon Hayward deserved a broken ankle because he was jumping around being a moron? https://twitter.com/RearAdBsBlog/status/928364293153804290 \u2026",
      {
        "neg": 0.296,
        "neu": 0.704,
        "pos": 0.0,
        "compound": -0.743
      }
    ],
    [
      "Lol gordon hayward got hurt n niggas had time",
      {
        "neg": 0.426,
        "neu": 0.368,
        "pos": 0.206,
        "compound": -0.4588
      }
    ],
    2017,
    3
  ]
}