{
  "mrvincecarter15": [
    [
      "# FLASHBACKFRIDAY When @ SacramentoKings Head Coach @ CoachJoerger tells you why @ MrVinceCarter15 didn't play in Post Game Interview!!! It was an Honor!!! # FANTRUTH # FBFpic.twitter.com/iQ4ql1shIo",
      {
        "neg": 0.077,
        "neu": 0.757,
        "pos": 0.165,
        "compound": 0.5158
      }
    ],
    [
      "Best in game DUNKER of all time......",
      {
        "neg": 0.0,
        "neu": 0.588,
        "pos": 0.412,
        "compound": 0.6369
      }
    ],
    [
      "@ mrvincecarter15 started it, @ chrisbosh continued it, @ JmCalderon kept it steady, @ DeMar_DeRozan confirmed the loyalty, @ Klow7 holds it down for a life long @ Raptors fan # WeTheNorthpic.twitter.com/Np351mnN9Q",
      {
        "neg": 0.0,
        "neu": 0.791,
        "pos": 0.209,
        "compound": 0.7003
      }
    ],
    [
      "@ mrvincecarter15 big fan I'm 14 years old and I've been playing on a basketball team for 5 years now I have autism but I'm high functioning so I can still function and act normal u still got game I trying to sow my jersey back together :) . pic.twitter.com/1qd6GwDtX7",
      {
        "neg": 0.0,
        "neu": 0.847,
        "pos": 0.153,
        "compound": 0.7227
      }
    ],
    [
      "The work of @ mrvincecarter15 ??",
      {
        "neg": 0.0,
        "neu": 1.0,
        "pos": 0.0,
        "compound": 0.0
      }
    ],
    [
      "Another Angle!pic.twitter.com/HkSA4PuUo3",
      {
        "neg": 0.0,
        "neu": 1.0,
        "pos": 0.0,
        "compound": 0.0
      }
    ],
    [
      "@ mrvincecarter15",
      {
        "neg": 0.0,
        "neu": 1.0,
        "pos": 0.0,
        "compound": 0.0
      }
    ],
    [
      "And now the oldest player in the league https://www.fivefifthsculture.com/blog/2017/3/2/vince-carter-is-the-oldest-player-in-the-nba \u2026",
      {
        "neg": 0.0,
        "neu": 1.0,
        "pos": 0.0,
        "compound": 0.0
      }
    ],
    [
      "My n*gga helllll no !!!!! @ mrvincecarter15 https://twitter.com/timelesssports_/status/1060939972168114176 \u2026",
      {
        "neg": 0.36,
        "neu": 0.64,
        "pos": 0.0,
        "compound": -0.5216
      }
    ],
    [
      "(2000) Vince Carter throws down the windmill alley-oop like it's nothing. SHEESH. @ mrvincecarter15 pic.twitter.com/XEorr4x37B",
      {
        "neg": 0.0,
        "neu": 0.839,
        "pos": 0.161,
        "compound": 0.3612
      }
    ],
    [
      "@ mrvincecarter15 Good morning",
      {
        "neg": 0.0,
        "neu": 0.408,
        "pos": 0.592,
        "compound": 0.4404
      }
    ],
    [
      "3 Pts vs Knicks @ mrvincecarter15 http://youtu.be/4vTF4SSjkJQ?a",
      {
        "neg": 0.0,
        "neu": 1.0,
        "pos": 0.0,
        "compound": 0.0
      }
    ],
    [
      ". @ kobebryant & @ mrvincecarter15 on the same college team https://twitter.com/HeelsUpdates/status/1060749417039478786 \u2026",
      {
        "neg": 0.0,
        "neu": 1.0,
        "pos": 0.0,
        "compound": 0.0
      }
    ],
    [
      "@ mrvincecarter15 hope you will take the trouble of traveeling to Salem and we can see whether Mudra is a real game changer or is it damp squib...READY FOR CHALLENGE???",
      {
        "neg": 0.081,
        "neu": 0.754,
        "pos": 0.165,
        "compound": 0.4162
      }
    ],
    [
      ". @ mrvincecarter15 all day long. Sorry, Vince. I didn\u2019t steal it, just borrowed it once in a moment of failing creativity. I\u2019ve definitely thought about \u201cO Canada\u201d for @ Obrissy. # OrangeNationhttps://twitter.com/MartinBahl1/status/1060737510047932417 \u2026",
      {
        "neg": 0.222,
        "neu": 0.627,
        "pos": 0.151,
        "compound": -0.3612
      }
    ],
    [
      "Thanks for including me, even if only as the token white athlete!",
      {
        "neg": 0.0,
        "neu": 0.775,
        "pos": 0.225,
        "compound": 0.4926
      }
    ],
    [
      "I was asked to name my top five professional athletes of all time. @ MikeTyson @ LennyDykstra @ KingJames @ mrvincecarter15 @ TikiBarber Who do you have in yours? # athletes # sports",
      {
        "neg": 0.0,
        "neu": 0.93,
        "pos": 0.07,
        "compound": 0.2023
      }
    ],
    [
      "@ mrvincecarter15 give us one last dunk contest performance",
      {
        "neg": 0.0,
        "neu": 1.0,
        "pos": 0.0,
        "compound": 0.0
      }
    ],
    [
      "@ mrvincecarter15 https://twitter.com/DallasPH45/status/1059972663702155264 \u2026",
      {
        "neg": 0.0,
        "neu": 1.0,
        "pos": 0.0,
        "compound": 0.0
      }
    ],
    [
      "My top 5 fave players of all time and who I pattered my game from: 1) @ KingJames (Lebron James) 2) @ TheRealLJ2 (Larry Johnson) 3) @ mrvincecarter15(Vince Carter) 4) @ Jumpman23(Michael Jordan) 5)Charles Barkley",
      {
        "neg": 0.0,
        "neu": 0.852,
        "pos": 0.148,
        "compound": 0.5719
      }
    ],
    [
      "@ mrvincecarter15 do you ever think of the missed oppurtunity of having Chauncey Billups as a teammate early on in your career? and if so, how big of an impact do you think he would have had in your career?",
      {
        "neg": 0.065,
        "neu": 0.935,
        "pos": 0.0,
        "compound": -0.3736
      }
    ],
    [
      "@ 1MrBigShot not to bring up any bad memories but coming from the man himself, what were the reasons/excuses Toronto and Boston gave up on you so early on in your career? and do you ever think about the missed opportunities of playing with @ mrvincecarter15 and @ paulpierce34 ?",
      {
        "neg": 0.095,
        "neu": 0.792,
        "pos": 0.112,
        "compound": 0.2287
      }
    ],
    [
      "If i knew you was at the game I would\u2019ve came and holla\u2019d at ya bro",
      {
        "neg": 0.0,
        "neu": 1.0,
        "pos": 0.0,
        "compound": 0.0
      }
    ],
    [
      "@ mrvincecarter15",
      {
        "neg": 0.0,
        "neu": 1.0,
        "pos": 0.0,
        "compound": 0.0
      }
    ],
    [
      "@ KyleKorver added 2 3-Pointers last night to make it 32 3-Pointers @ StephenCurry30 has to make to tie him and 33 to pass. amal @ JCrossover needs to make 33 3-Pointers to tie Steph or 34 to pass. @ mrvincecarter15 is slowly speeding up the chart and has 22 to pass @ paulpierce34 .pic.twitter.com/VW2qYoAwo4",
      {
        "neg": 0.0,
        "neu": 1.0,
        "pos": 0.0,
        "compound": 0.0
      }
    ],
    [
      "3 Pts vs Knicks @ mrvincecarter15 http://youtu.be/4vTF4SSjkJQ?a",
      {
        "neg": 0.0,
        "neu": 1.0,
        "pos": 0.0,
        "compound": 0.0
      }
    ],
    [
      "3 Pts vs Knicks @ mrvincecarter15 http://youtu.be/4vTF4SSjkJQ?a",
      {
        "neg": 0.0,
        "neu": 1.0,
        "pos": 0.0,
        "compound": 0.0
      }
    ],
    [
      "Great to see your getting back on the @ Raptors bandwagon. There's always room for @ MapleLeafs fans @ mrvincecarter15 is playing with the @ ATLHawks this year, being a mentor to a young team. Next year... who knows... maybe #15 comes home!",
      {
        "neg": 0.0,
        "neu": 0.85,
        "pos": 0.15,
        "compound": 0.7345
      }
    ],
    [
      "Can you do Mike Conley, Jaren Jackson Jr. Or Marc Gasol",
      {
        "neg": 0.0,
        "neu": 1.0,
        "pos": 0.0,
        "compound": 0.0
      }
    ],
    [
      "@ mrvincecarter15 what do you think of this tattoo? pic.twitter.com/XbzeZi7Sr7",
      {
        "neg": 0.0,
        "neu": 1.0,
        "pos": 0.0,
        "compound": 0.0
      }
    ],
    [
      "pic.twitter.com/z9vjaBbitC",
      {
        "neg": 0.0,
        "neu": 1.0,
        "pos": 0.0,
        "compound": 0.0
      }
    ],
    [
      "@ mrvincecarter15... el hombre que puso en el mapa a # Toronto!!!",
      {
        "neg": 0.0,
        "neu": 1.0,
        "pos": 0.0,
        "compound": 0.0
      }
    ],
    [
      "@ mrvincecarter15 VC, me and my gf r travelling 7500 miles from HongKong just for you, will b at Lakers v Hawks game and im a big fans since your rookie year! Can we take a selfie on 11 Nov? We will b sitting on row 5 behind the away team bench...pls",
      {
        "neg": 0.0,
        "neu": 1.0,
        "pos": 0.0,
        "compound": 0.0
      }
    ],
    [
      "Can me and my gf take a selfie with @ JLin7 on 11 Nov Lakers game? We travelled 7500 miles to watch him and @ mrvincecarter15 ...",
      {
        "neg": 0.0,
        "neu": 1.0,
        "pos": 0.0,
        "compound": 0.0
      }
    ],
    [
      "@ mrvincecarter15 left an incredible impact in Toronto & on a whole. You cared more about the youth in TO than elected officials. We remember the basketball court u built in Rexdale & charity games you hosted. We love u, you\u2019re an amazing person! You inspired a generation.",
      {
        "neg": 0.0,
        "neu": 0.684,
        "pos": 0.316,
        "compound": 0.9523
      }
    ],
    [
      "@ mrvincecarter15 make this kid happy with a reply, would you please?! https://twitter.com/Aowsbaker83/status/803981959282171904 \u2026",
      {
        "neg": 0.0,
        "neu": 0.715,
        "pos": 0.285,
        "compound": 0.6114
      }
    ],
    [
      "Aaron Gordon needs to channel his inner @ mrvincecarter15",
      {
        "neg": 0.0,
        "neu": 1.0,
        "pos": 0.0,
        "compound": 0.0
      }
    ],
    [
      "Can some contending @ NBA team please trade for @ mrvincecarter15",
      {
        "neg": 0.0,
        "neu": 0.777,
        "pos": 0.223,
        "compound": 0.3182
      }
    ],
    [
      "At what age did u dunk for the 1st time?",
      {
        "neg": 0.0,
        "neu": 1.0,
        "pos": 0.0,
        "compound": 0.0
      }
    ],
    [
      "Can u do one for De'Aaron Fox",
      {
        "neg": 0.0,
        "neu": 1.0,
        "pos": 0.0,
        "compound": 0.0
      }
    ],
    [
      "@ mrvincecarter15",
      {
        "neg": 0.0,
        "neu": 1.0,
        "pos": 0.0,
        "compound": 0.0
      }
    ],
    [
      "This is the best photo i have seen on this app in years",
      {
        "neg": 0.0,
        "neu": 0.724,
        "pos": 0.276,
        "compound": 0.6369
      }
    ],
    [
      "What a group --WOW. Leapin' Larry Nance",
      {
        "neg": 0.0,
        "neu": 1.0,
        "pos": 0.0,
        "compound": 0.0
      }
    ],
    [
      "This man is pure motivation lol if i can just grab rim at 40 I'll be happy",
      {
        "neg": 0.0,
        "neu": 0.594,
        "pos": 0.406,
        "compound": 0.836
      }
    ],
    [
      "@ mrvincecarter15 https://twitter.com/ESPNNBA/status/1059985346107203584 \u2026",
      {
        "neg": 0.0,
        "neu": 1.0,
        "pos": 0.0,
        "compound": 0.0
      }
    ],
    [
      "Congratulations @ mrvincecarter15 pic.twitter.com/PoD3WyhaaD",
      {
        "neg": 0.0,
        "neu": 0.339,
        "pos": 0.661,
        "compound": 0.5994
      }
    ],
    [
      "2018 Mitchell Robinson 180 alley oop",
      {
        "neg": 0.0,
        "neu": 1.0,
        "pos": 0.0,
        "compound": 0.0
      }
    ],
    [
      "In 2010 blake griffin received oral sex while he attempted dat dunk # unbelievable",
      {
        "neg": 0.0,
        "neu": 0.87,
        "pos": 0.13,
        "compound": 0.2023
      }
    ],
    [
      "Top rookie dunks in NBA History: 1999: @ mrvincecarter15 vs the Pacers 2010: @ blakegriffin23 on Mozgov 1985: Jordan's cradule dunk vs the Knicks # NBA # NBATwitter # TheJump",
      {
        "neg": 0.0,
        "neu": 0.93,
        "pos": 0.07,
        "compound": 0.2023
      }
    ],
    [
      "\"Do not listen to your cousin. Listen to me\" - @ Rachel__Nichols @ mrvincecarter15 # NBATwitter # TheJump # TrueToAtlantahttps://twitter.com/NBATheJumpFP/status/1060263138455625729 \u2026",
      {
        "neg": 0.0,
        "neu": 1.0,
        "pos": 0.0,
        "compound": 0.0
      }
    ],
    [
      "pic.twitter.com/aqropl49e9",
      {
        "neg": 0.0,
        "neu": 1.0,
        "pos": 0.0,
        "compound": 0.0
      }
    ],
    [
      "Rock with me if you need Beats Hit me up... # hiphop # rapbeats # samples # mpcrenaissance # akaimpc # akaipro # LogicproX # production # producer # producerlife # beatmaker # imakebeats @ mrvincecarter15 Half Man Half Amazing pic.twitter.com/Pqv2krQ2Ej",
      {
        "neg": 0.0,
        "neu": 0.877,
        "pos": 0.123,
        "compound": 0.5859
      }
    ],
    [
      "- @ swish41 : I\u2019d love to have your hoops - @ mrvincecarter15 : I\u2019d love to have your hair pic.twitter.com/C0ZqSrNio6",
      {
        "neg": 0.0,
        "neu": 0.607,
        "pos": 0.393,
        "compound": 0.8555
      }
    ],
    [
      "@ mrvincecarter15 the best! https://twitter.com/EsportesUSA_/status/1060236093063421952 \u2026",
      {
        "neg": 0.0,
        "neu": 0.4,
        "pos": 0.6,
        "compound": 0.6696
      }
    ],
    [
      "The @ mrvincecarter15 one is intriguing. Of course I\u2019m biased.",
      {
        "neg": 0.208,
        "neu": 0.792,
        "pos": 0.0,
        "compound": -0.2732
      }
    ],
    [
      "I would give anything to see this moment re-created!! @ Rachel__Nichols You are on to something!! @ mrvincecarter15 @ Real_T_Mac # VCfor2019SlamDunkContestpic.twitter.com/dV0TGuMs2t",
      {
        "neg": 0.0,
        "neu": 1.0,
        "pos": 0.0,
        "compound": 0.0
      }
    ],
    [
      "NBALatam: \u00a1MilesBridges naci\u00f3 en 1998, a\u00f1o en el cual mrvincecarter15 debut\u00f3 en la # NBA!Anoche se midieron por primera vez\u2026 https://twitter.com/i/web/status/1060218678795530240 \u2026",
      {
        "neg": 0.0,
        "neu": 1.0,
        "pos": 0.0,
        "compound": 0.0
      }
    ],
    [
      "Damn!!!",
      {
        "neg": 1.0,
        "neu": 0.0,
        "pos": 0.0,
        "compound": -0.5538
      }
    ],
    [
      "\u00a1MilesBridges naci\u00f3 en 1998, a\u00f1o en el cual mrvincecarter15 debut\u00f3 en la # NBA! Anoche se midieron por primera vez y nos dejaron esta joyita pic.twitter.com/jZX3pUf6YX",
      {
        "neg": 0.0,
        "neu": 1.0,
        "pos": 0.0,
        "compound": 0.0
      }
    ],
    [
      "\u00a1 @ MilesBridges naci\u00f3 en 1998, a\u00f1o en el cual @ mrvincecarter15 debut\u00f3 en la # NBA! Anoche se midieron por primera vez y nos dejaron esta joyita pic.twitter.com/awf1Iwx2pM",
      {
        "neg": 0.0,
        "neu": 1.0,
        "pos": 0.0,
        "compound": 0.0
      }
    ],
    [
      "Maaannn 41 years of age! @ mrvincecarter15 https://twitter.com/NBA/status/1059967511066800128 \u2026",
      {
        "neg": 0.0,
        "neu": 1.0,
        "pos": 0.0,
        "compound": 0.0
      }
    ],
    [
      "@ mrvincecarter15 was drafted the same year @ TheTraeYoung was born now they out here hoopin togetherpic.twitter.com/EvsTSv8CLA",
      {
        "neg": 0.0,
        "neu": 1.0,
        "pos": 0.0,
        "compound": 0.0
      }
    ],
    [
      "Tiene cosas de @ mrvincecarter15",
      {
        "neg": 0.0,
        "neu": 1.0,
        "pos": 0.0,
        "compound": 0.0
      }
    ],
    [
      "Legend @ ATLHawks @ mrvincecarter15 @ DanielPlatzmanpic.twitter.com/ZpA9adFhqg",
      {
        "neg": 0.0,
        "neu": 1.0,
        "pos": 0.0,
        "compound": 0.0
      }
    ],
    [
      "@ mrvincecarter15 dunking at 42 is https://twitter.com/NBA/status/1059967511066800128 \u2026",
      {
        "neg": 0.0,
        "neu": 1.0,
        "pos": 0.0,
        "compound": 0.0
      }
    ],
    [
      "It\u2019s sad this doesn\u2019t have more likes",
      {
        "neg": 0.277,
        "neu": 0.447,
        "pos": 0.276,
        "compound": -0.0018
      }
    ],
    [
      "I was just about to message you to ask what the crowd REACTION was like after this!!!!",
      {
        "neg": 0.0,
        "neu": 0.804,
        "pos": 0.196,
        "compound": 0.5673
      }
    ],
    [
      "the art of the post-game. @ mrvincecarter15 way to keep schoolin' the young bucks.",
      {
        "neg": 0.0,
        "neu": 1.0,
        "pos": 0.0,
        "compound": 0.0
      }
    ],
    [
      "Aulinha de POST com o mrvincecarter15! O veterano girou pra dentro e botou pra baixo! # TrueToAtlantapic.twitter.com/nMjvHUsTlh",
      {
        "neg": 0.0,
        "neu": 1.0,
        "pos": 0.0,
        "compound": 0.0
      }
    ],
    [
      "Aulinha de POST com o @ mrvincecarter15! O veterano girou pra dentro e botou pra baixo! # TrueToAtlantapic.twitter.com/uUbkaEQPwt",
      {
        "neg": 0.0,
        "neu": 1.0,
        "pos": 0.0,
        "compound": 0.0
      }
    ],
    [
      "''MOTHERF****R!'' @ mrvincecarter15 Mic'd Up w/ @ SamuelLJackson Voice!http://youtu.be/JWYo-mBBvgQ?a",
      {
        "neg": 0.0,
        "neu": 1.0,
        "pos": 0.0,
        "compound": 0.0
      }
    ],
    [
      "@ mrvincecarter15 did you play against all Pro linebackers too? https://twitter.com/AndreBoyd1981/status/1060147441822023682 \u2026",
      {
        "neg": 0.0,
        "neu": 0.789,
        "pos": 0.211,
        "compound": 0.34
      }
    ],
    [
      "Based on my last retweet and more so what he\u2019s done in the prime of his career, my state of Florida needs to construct a statue of @ mrvincecarter15 as the greatest player to come from the state and greatest dunker in NBA history!! New generation of players need to pick his brain.",
      {
        "neg": 0.0,
        "neu": 0.845,
        "pos": 0.155,
        "compound": 0.8745
      }
    ],
    [
      "\u201c respect to @ mrvincecarter15\u201d @ MilesBridges throws down an early dunk of the year candidate vs the Hawks then pays tribute to Vince Carter with the \u201crev it up\u201d celebration!pic.twitter.com/FnPaQh5ZEp",
      {
        "neg": 0.0,
        "neu": 0.888,
        "pos": 0.112,
        "compound": 0.5255
      }
    ],
    [
      "Mate I watched it live and a thousand times since. WILD!!",
      {
        "neg": 0.0,
        "neu": 1.0,
        "pos": 0.0,
        "compound": 0.0
      }
    ],
    [
      "El duelo generacional salta por los aires: @ mrvincecarter15 (41 a\u00f1os) vs @ MilesBridges (20) # NBATop10 # Hornets30 https://www.marca.com/baloncesto/nba/2018/11/07/5be2a942e2704e828b8b45a1.html \u2026pic.twitter.com/l2irP61IIB",
      {
        "neg": 0.0,
        "neu": 1.0,
        "pos": 0.0,
        "compound": 0.0
      }
    ],
    [
      "7 Pts 1 VINTAGE DUNK vs Hornets @ mrvincecarter15 http://youtu.be/X0XaIqSxXJ0?a",
      {
        "neg": 0.0,
        "neu": 1.0,
        "pos": 0.0,
        "compound": 0.0
      }
    ],
    [
      "VINSANITY! @ mrvincecarter15 VINTAGE Spinning DUNK vs Hornets! Half Man Half Amazing http://youtu.be/CZ84oL_-SD8?a",
      {
        "neg": 0.0,
        "neu": 0.715,
        "pos": 0.285,
        "compound": 0.658
      }
    ],
    [
      "@ mrvincecarter15 was snubbed from the @ NBA\u2019s Top 5 Plays of the Night.....",
      {
        "neg": 0.203,
        "neu": 0.541,
        "pos": 0.257,
        "compound": -0.0516
      }
    ],
    [
      "SHEESH",
      {
        "neg": 0.0,
        "neu": 1.0,
        "pos": 0.0,
        "compound": 0.0
      }
    ],
    [
      "Thank you. Glad you're not a hater",
      {
        "neg": 0.0,
        "neu": 0.277,
        "pos": 0.723,
        "compound": 0.7803
      }
    ],
    [
      "@ lilhaitian_so9O",
      {
        "neg": 0.0,
        "neu": 1.0,
        "pos": 0.0,
        "compound": 0.0
      }
    ],
    [
      "@ mrvincecarter15 the most true baller of all time. Has gave his heart, soul, and life (and knees) into basketball. Doesn\u2019t ring chase. The man just loves basketball.",
      {
        "neg": 0.0,
        "neu": 0.786,
        "pos": 0.214,
        "compound": 0.7778
      }
    ],
    [
      "miles ... that was one of the greatest dunks ive ever witnessed in a basketball game. i know vince would be proud if you weren't doing it to his team lmao",
      {
        "neg": 0.0,
        "neu": 0.699,
        "pos": 0.301,
        "compound": 0.9042
      }
    ],
    [
      "If @ JHarden13 ate @ mrvincecarter15 you\u2019d get @ ZionW32 # Duke",
      {
        "neg": 0.0,
        "neu": 1.0,
        "pos": 0.0,
        "compound": 0.0
      }
    ],
    [
      "So, husband says @ ZionW32 is a mix of @ MacBo50, @ mrvincecarter15, and @ NBAonTNT Charles Barkley! He\u2019s putting on a show tonight! # Duke # Dukebasketball @ DukeMBB @ KentuckyMBBpic.twitter.com/2cNfcnLbKQ",
      {
        "neg": 0.0,
        "neu": 1.0,
        "pos": 0.0,
        "compound": 0.0
      }
    ],
    [
      "@ mrvincecarter15 Not all Hero\u2019s wear capes!! https://twitter.com/WorldWideWob/status/1059966631806492672 \u2026",
      {
        "neg": 0.0,
        "neu": 1.0,
        "pos": 0.0,
        "compound": 0.0
      }
    ],
    [
      "Dawgggggg that was a nasty dunk",
      {
        "neg": 0.474,
        "neu": 0.526,
        "pos": 0.0,
        "compound": -0.5574
      }
    ],
    [
      "That's beautiful! You're going to be great my man",
      {
        "neg": 0.0,
        "neu": 0.458,
        "pos": 0.542,
        "compound": 0.8516
      }
    ],
    [
      "@ mrvincecarter15 i think you should return to the dunk contest!!!!! https://twitter.com/NBA/status/1059967511066800128 \u2026",
      {
        "neg": 0.0,
        "neu": 1.0,
        "pos": 0.0,
        "compound": 0.0
      }
    ],
    [
      "Smh BRO!!! Chilllll out MB!!",
      {
        "neg": 0.464,
        "neu": 0.536,
        "pos": 0.0,
        "compound": -0.5374
      }
    ],
    [
      "So nasty",
      {
        "neg": 0.796,
        "neu": 0.204,
        "pos": 0.0,
        "compound": -0.5984
      }
    ],
    [
      "Aha I was wondering if you were gonna say anything about the celebration good shit man",
      {
        "neg": 0.185,
        "neu": 0.667,
        "pos": 0.149,
        "compound": -0.1779
      }
    ],
    [
      "respect to @ mrvincecarter15 https://twitter.com/hornets/status/1059969237983215616 \u2026",
      {
        "neg": 0.0,
        "neu": 0.492,
        "pos": 0.508,
        "compound": 0.4767
      }
    ],
    [
      "I shook his hand. Omg",
      {
        "neg": 0.212,
        "neu": 0.303,
        "pos": 0.485,
        "compound": 0.4215
      }
    ],
    [
      "Total respect for you @ mrvincecarter15. Going strong in the Association since \u201898. Tip of the cap.",
      {
        "neg": 0.0,
        "neu": 0.686,
        "pos": 0.314,
        "compound": 0.7506
      }
    ],
    [
      "LOL. come on bro, dont make vince wanna leave early",
      {
        "neg": 0.094,
        "neu": 0.628,
        "pos": 0.277,
        "compound": 0.516
      }
    ],
    [
      "S/o to @ mrvincecarter15 https://twitter.com/nicekicks/status/1059979921265577984 \u2026",
      {
        "neg": 0.0,
        "neu": 1.0,
        "pos": 0.0,
        "compound": 0.0
      }
    ],
    [
      "Vince disrespect every man in every poster why not?",
      {
        "neg": 0.259,
        "neu": 0.741,
        "pos": 0.0,
        "compound": -0.4215
      }
    ],
    [
      "Con esta canasta, @ mrvincecarter15 supera a Jerry West y se ubica en el lugar de la historia en canastas anotadas (9,017). # TrueToAtlanta pic.twitter.com/Dd6X5101Mh",
      {
        "neg": 0.0,
        "neu": 1.0,
        "pos": 0.0,
        "compound": 0.0
      }
    ],
    [
      "Congrats @ mrvincecarter15",
      {
        "neg": 0.0,
        "neu": 0.227,
        "pos": 0.773,
        "compound": 0.5267
      }
    ],
    [
      "Shout out to @ mrvincecarter15 for passing the logo for 21st all time. A lot of those points were posters in our rooms",
      {
        "neg": 0.0,
        "neu": 1.0,
        "pos": 0.0,
        "compound": 0.0
      }
    ],
    [
      "Love it. @ mrvincecarter15 will always be one of my favorites. https://twitter.com/NBA/status/1059995111638089729 \u2026",
      {
        "neg": 0.0,
        "neu": 0.562,
        "pos": 0.438,
        "compound": 0.7906
      }
    ],
    [
      "Vince is overrated",
      {
        "neg": 0.0,
        "neu": 1.0,
        "pos": 0.0,
        "compound": 0.0
      }
    ],
    [
      "@ mrvincecarter15 just passed the logo. # nba",
      {
        "neg": 0.0,
        "neu": 1.0,
        "pos": 0.0,
        "compound": 0.0
      }
    ],
    [
      "A fan told @ mrvincecarter15 he only has 4 points. pic.twitter.com/LH3rV2Wo6O",
      {
        "neg": 0.0,
        "neu": 0.753,
        "pos": 0.247,
        "compound": 0.3182
      }
    ],
    [
      "@ mrvincecarter15 u should retire as a Raptor VC",
      {
        "neg": 0.0,
        "neu": 1.0,
        "pos": 0.0,
        "compound": 0.0
      }
    ],
    [
      "Rev it up @ mrvincecarter15 https://twitter.com/WorldWideWob/status/1059966631806492672 \u2026",
      {
        "neg": 0.0,
        "neu": 1.0,
        "pos": 0.0,
        "compound": 0.0
      }
    ],
    [
      "Lol the disrespect",
      {
        "neg": 0.424,
        "neu": 0.152,
        "pos": 0.424,
        "compound": 0.0
      }
    ],
    [
      "Vince McFly! @ mrvincecarter15 stepped into the time machine and went back to the future with this dunk # NBA # TrueToAtlantapic.twitter.com/ZtRUHW5yzY",
      {
        "neg": 0.0,
        "neu": 1.0,
        "pos": 0.0,
        "compound": 0.0
      }
    ],
    [
      "These young kids can\u2019t hang with @ mrvincecarter15 pic.twitter.com/2cpqqAS5wp",
      {
        "neg": 0.0,
        "neu": 1.0,
        "pos": 0.0,
        "compound": 0.0
      }
    ],
    [
      "No te retires nunca Don Vicente!! @ mrvincecarter15 https://twitter.com/NBA/status/1059967511066800128 \u2026",
      {
        "neg": 0.285,
        "neu": 0.715,
        "pos": 0.0,
        "compound": -0.4184
      }
    ],
    [
      "Yo slam dunk contest this year please @ mrvincecarter15",
      {
        "neg": 0.239,
        "neu": 0.55,
        "pos": 0.211,
        "compound": -0.0772
      }
    ],
    [
      "# NBA \u2502 Vintage @ mrvincecarter15 # TrueToAtlantapic.twitter.com/4TsVMaTTy9",
      {
        "neg": 0.0,
        "neu": 1.0,
        "pos": 0.0,
        "compound": 0.0
      }
    ],
    [
      "# NBA \u2502 Vintage @ mrvincecarter15 # TrueToAtlantapic.twitter.com/RZ7nXqv80i",
      {
        "neg": 0.0,
        "neu": 1.0,
        "pos": 0.0,
        "compound": 0.0
      }
    ],
    [
      "Pay homage to @ mrvincecarter15 https://twitter.com/SportsCenter/status/1059974736799776770 \u2026",
      {
        "neg": 0.259,
        "neu": 0.741,
        "pos": 0.0,
        "compound": -0.1027
      }
    ],
    [
      "Thank you for being my favorite all time player @ mrvincecarter15 https://twitter.com/WorldWideWob/status/1059966631806492672 \u2026",
      {
        "neg": 0.0,
        "neu": 0.621,
        "pos": 0.379,
        "compound": 0.6705
      }
    ],
    [
      "",
      {
        "neg": 0.0,
        "neu": 0.0,
        "pos": 0.0,
        "compound": 0.0
      }
    ],
    [
      "Never lost it! @ mrvincecarter15 # VC15https://twitter.com/ATLHawks/status/1059967258397560832 \u2026",
      {
        "neg": 0.0,
        "neu": 0.64,
        "pos": 0.36,
        "compound": 0.308
      }
    ],
    [
      "Yessir!!!! @ mrvincecarter15 # VC15https://twitter.com/NBA/status/1059967511066800128 \u2026",
      {
        "neg": 0.0,
        "neu": 1.0,
        "pos": 0.0,
        "compound": 0.0
      }
    ],
    [
      "VC is 41!!! # halfmanhalfamazing ! @ mrvincecarter15 https://twitter.com/NBA/status/1059967511066800128 \u2026",
      {
        "neg": 0.0,
        "neu": 1.0,
        "pos": 0.0,
        "compound": 0.0
      }
    ],
    [
      "Como en los viejos tiempos, @ mrvincecarter15 con la clavada. # TrueToAtlantapic.twitter.com/vHRVqfdO2b",
      {
        "neg": 0.0,
        "neu": 1.0,
        "pos": 0.0,
        "compound": 0.0
      }
    ],
    [
      ". @ mrvincecarter15 WHAT are you made of https://twitter.com/ATLHawks/status/1059967258397560832 \u2026",
      {
        "neg": 0.0,
        "neu": 1.0,
        "pos": 0.0,
        "compound": 0.0
      }
    ],
    [
      "Dunk contest please @ mrvincecarter15",
      {
        "neg": 0.0,
        "neu": 0.566,
        "pos": 0.434,
        "compound": 0.3182
      }
    ],
    [
      "VINTAGE @ mrvincecarter15 !!!! Sweet dunk!!!! https://twitter.com/NBA/status/1059967511066800128 \u2026",
      {
        "neg": 0.0,
        "neu": 0.545,
        "pos": 0.455,
        "compound": 0.6331
      }
    ],
    [
      "@ mrvincecarter15 still has bounce!! # vinsanity # Hawks # NBA",
      {
        "neg": 0.0,
        "neu": 1.0,
        "pos": 0.0,
        "compound": 0.0
      }
    ],
    [
      "Vintage @ mrvincecarter15 vs. @ hornets. # TrueToAtlanta (: @ NBA)pic.twitter.com/IXdVW5HwDl",
      {
        "neg": 0.0,
        "neu": 0.652,
        "pos": 0.348,
        "compound": 0.4939
      }
    ],
    [
      "This is one of the reasons why @ Rachel__Nichols has been campaigning for @ mrvincecarter15 to be in the 2019 dunk contest this year! # NBATwitter # TheJumppic.twitter.com/BCE0UaYcPt",
      {
        "neg": 0.0,
        "neu": 1.0,
        "pos": 0.0,
        "compound": 0.0
      }
    ],
    [
      "Never leave us @ mrvincecarter15 pic.twitter.com/nIiqz67Bp8",
      {
        "neg": 0.0,
        "neu": 0.777,
        "pos": 0.223,
        "compound": 0.0382
      }
    ],
    [
      "Yo, do you regenerating? @ mrvincecarter15 https://twitter.com/NBA/status/1059967511066800128 \u2026",
      {
        "neg": 0.0,
        "neu": 1.0,
        "pos": 0.0,
        "compound": 0.0
      }
    ],
    [
      "Every year it seems, @ mrvincecarter15 seems to have a little something extra in his legs when he gets near North Carolina and Toronto",
      {
        "neg": 0.0,
        "neu": 1.0,
        "pos": 0.0,
        "compound": 0.0
      }
    ],
    [
      "We see you @ mrvincecarter15!! # TruetoAtlanta",
      {
        "neg": 0.0,
        "neu": 1.0,
        "pos": 0.0,
        "compound": 0.0
      }
    ],
    [
      "Oh Vicente! Incre\u00edble lo de este t\u00edo!! @ mrvincecarter15",
      {
        "neg": 0.0,
        "neu": 1.0,
        "pos": 0.0,
        "compound": 0.0
      }
    ],
    [
      "Fact: @ mrvincecarter15 can still get it done... @ ATLHawks @ NBApic.twitter.com/8y9Pm9IwH9",
      {
        "neg": 0.0,
        "neu": 1.0,
        "pos": 0.0,
        "compound": 0.0
      }
    ],
    [
      "@ Bakari_Sellers my brother can you get your bottoms fixed you\u2019re on national television representing us cc: @ mrvincecarter15 @ EllenRucker @ CNN # BlackTwitterpic.twitter.com/fl9pmaOYRz",
      {
        "neg": 0.0,
        "neu": 1.0,
        "pos": 0.0,
        "compound": 0.0
      }
    ],
    [
      "# YOURE TRULY AN # HALFMAN & # HALFAMAZING",
      {
        "neg": 0.0,
        "neu": 0.58,
        "pos": 0.42,
        "compound": 0.4404
      }
    ],
    [
      "@ mrvincecarter15 gotta go out with a bang, tryna enter that dunk contest this year??",
      {
        "neg": 0.0,
        "neu": 1.0,
        "pos": 0.0,
        "compound": 0.0
      }
    ],
    [
      "I Can\u2019t Find A @ mrvincecarter15 @ SacramentoKings Jersey Anywhere........pic.twitter.com/zeoltwHBeO",
      {
        "neg": 0.0,
        "neu": 1.0,
        "pos": 0.0,
        "compound": 0.0
      }
    ],
    [
      "Dunker of all time!!!! Near the top of the backboard with ease!!! Repost from vintagevinsanity - mrvincecarter15 effortless warmup dunks from his legendary dunk contest in 2000. These\u2026 https://www.instagram.com/p/Bp2LJy2nZCL/?utm_source=ig_twitter_share&igshid=1h1jzvgjyywf0 \u2026",
      {
        "neg": 0.0,
        "neu": 0.784,
        "pos": 0.216,
        "compound": 0.7067
      }
    ],
    [
      "Except Frederic Weis was a 7'2\"",
      {
        "neg": 0.0,
        "neu": 1.0,
        "pos": 0.0,
        "compound": 0.0
      }
    ],
    [
      "@ mrvincecarter15 should join the 2019 dunk contest! https://twitter.com/ESPNNBA/status/1057060441086705665 \u2026",
      {
        "neg": 0.0,
        "neu": 0.737,
        "pos": 0.263,
        "compound": 0.3595
      }
    ],
    [
      "@ mrvincecarter15 Vince has to get in the dunk contest this year .... it would be insane pic.twitter.com/gCtEcVNbaD",
      {
        "neg": 0.144,
        "neu": 0.856,
        "pos": 0.0,
        "compound": -0.4019
      }
    ],
    [
      "AWESOME",
      {
        "neg": 0.0,
        "neu": 0.0,
        "pos": 1.0,
        "compound": 0.6249
      }
    ],
    [
      "I\u2019m sorry, but Greg Monroe should not be allowed to wear the Raptors #15. That belongs to @ mrvincecarter15",
      {
        "neg": 0.063,
        "neu": 0.937,
        "pos": 0.0,
        "compound": -0.0387
      }
    ],
    [
      "\"A moment to savour. Two generational greats who can still play to this day. Side-by-side after going toe-to-toe for what looks like the last time\"... https://basketballbuzz.ca/nba/game-recognizes-game-swapping-nba-jerseys-is-the-new-thing \u2026 @ MiamiHEAT @ DwyaneWade @ MrVinceCarter15 @ ATLHawks @ NBA @ NBAHistory # ViceNights # NBA",
      {
        "neg": 0.0,
        "neu": 0.867,
        "pos": 0.133,
        "compound": 0.5994
      }
    ],
    [
      "After @ ATLHawks game on Saturday, @ DwyaneWade exchanged jerseys with @ mrvincecarter15. Who will it be tonight from @ DetroitPistons ??",
      {
        "neg": 0.0,
        "neu": 1.0,
        "pos": 0.0,
        "compound": 0.0
      }
    ],
    [
      "Would you want to see @ mrvincecarter15 enter the dunk contest?",
      {
        "neg": 0.0,
        "neu": 0.874,
        "pos": 0.126,
        "compound": 0.0772
      }
    ],
    [
      "Great game Sat vs Miami@mrvincecarter15",
      {
        "neg": 0.0,
        "neu": 0.494,
        "pos": 0.506,
        "compound": 0.6249
      }
    ],
    [
      "@ mrvincecarter15 would still throw that down",
      {
        "neg": 0.0,
        "neu": 1.0,
        "pos": 0.0,
        "compound": 0.0
      }
    ],
    [
      "@ Raptors and da @ Bucks are the best two Teams in the East. @ celtics will be just fine. As 4 the best # Raptors Player of all time it's @ DeMar_DeRozan but @ mrvincecarter15 Gave more Highlight plays # TimAndSid # Sportsnet # TorontoRaptors # WeTheNorth # DeMarDeRozan # NorthOverEverything",
      {
        "neg": 0.0,
        "neu": 0.723,
        "pos": 0.277,
        "compound": 0.9013
      }
    ],
    [
      "",
      {
        "neg": 0.0,
        "neu": 0.0,
        "pos": 0.0,
        "compound": 0.0
      }
    ],
    [
      "November 5, 1999: @ mrvincecarter15 gets eye level with the rim for the two-handed flush. # TheJump distant replay.pic.twitter.com/jzYIbzQ9vT",
      {
        "neg": 0.0,
        "neu": 1.0,
        "pos": 0.0,
        "compound": 0.0
      }
    ],
    [
      "Love it!",
      {
        "neg": 0.0,
        "neu": 0.182,
        "pos": 0.818,
        "compound": 0.6696
      }
    ],
    [
      "Just in case you forgot @ mrvincecarter15 is the best drunker of all time. All. Time. No discussion. # NBA",
      {
        "neg": 0.098,
        "neu": 0.714,
        "pos": 0.188,
        "compound": 0.4588
      }
    ],
    [
      ". @ Rachel__Nichols and # TheJump are campaigning for you @ mrvincecarter15 to be in this year's dunk contest! # NBATwitter # TheJump # MakeOrMissLeaguepic.twitter.com/KfLVUnErtr",
      {
        "neg": 0.0,
        "neu": 1.0,
        "pos": 0.0,
        "compound": 0.0
      }
    ],
    [
      "Put @ mrvincecarter15 in the dunk contest this season ...",
      {
        "neg": 0.0,
        "neu": 1.0,
        "pos": 0.0,
        "compound": 0.0
      }
    ],
    [
      "Miss: Age; Should 41-year-old @ mrvincecarter15 enter the dunk contest? # NBATwitter # TheJump # MakeOrMissLeaguehttps://twitter.com/NBATheJumpFP/status/1059539734731603970 \u2026",
      {
        "neg": 0.127,
        "neu": 0.873,
        "pos": 0.0,
        "compound": -0.1531
      }
    ],
    [
      "Distant Replay # OTD: November 5, 1999 - @ CharlesOakley34 with the alley-oop pass to @ mrvincecarter15 vs the Nets! # NBATwitter # TheJump # WeTheNorth",
      {
        "neg": 0.0,
        "neu": 1.0,
        "pos": 0.0,
        "compound": 0.0
      }
    ],
    [
      "@ mrvincecarter15 I just had my first child, named him after you as I grew up watching you. He is 9 weeks young. Ill be attending pacer game new years eve with my newborn. Would love a photo with you and my son if I make my way down by your bench during warm up! Thanks!",
      {
        "neg": 0.048,
        "neu": 0.788,
        "pos": 0.164,
        "compound": 0.7772
      }
    ],
    [
      "Comic book I\u2019m working on about @ mrvincecarter15 pic.twitter.com/7CZQzGktmm",
      {
        "neg": 0.0,
        "neu": 1.0,
        "pos": 0.0,
        "compound": 0.0
      }
    ],
    [
      "Penny and AI were my guys growing up along w mr @ mrvincecarter15 https://twitter.com/Ballislife/status/1059492459267395584 \u2026",
      {
        "neg": 0.0,
        "neu": 0.866,
        "pos": 0.134,
        "compound": 0.1779
      }
    ],
    [
      "# SportscasterU Class of 2011. @ dahntay1 @ ShaunLivingston @ Matt13Carroll @ boykinsacademy @ andre @ TheRyanHollins @ mrvincecarter15 thank you @ MattPark1 @ GerryMatalonpic.twitter.com/1OHxs9hu44",
      {
        "neg": 0.0,
        "neu": 0.848,
        "pos": 0.152,
        "compound": 0.3612
      }
    ],
    [
      "Half-Man. Half-Pixels. ( @ mrvincecarter15) pic.twitter.com/HMWkrI2P47",
      {
        "neg": 0.0,
        "neu": 1.0,
        "pos": 0.0,
        "compound": 0.0
      }
    ],
    [
      "Classic classic. Thanks gentlemen. Let\u2019s go",
      {
        "neg": 0.0,
        "neu": 0.633,
        "pos": 0.367,
        "compound": 0.4404
      }
    ],
    [
      "@ mrvincecarter15 https://SoundCloud.com/billylean/beware-original-mix \u2026",
      {
        "neg": 0.0,
        "neu": 1.0,
        "pos": 0.0,
        "compound": 0.0
      }
    ],
    [
      "Good players",
      {
        "neg": 0.0,
        "neu": 0.256,
        "pos": 0.744,
        "compound": 0.4404
      }
    ],
    [
      "The respect",
      {
        "neg": 0.0,
        "neu": 0.244,
        "pos": 0.756,
        "compound": 0.4767
      }
    ],
    [
      "Se va retirar @ mrvincecarter15, se retir\u00f3 @ manuginobili... Que triste ver que se van tus h\u00e9roes. @ NBALatam # NBA",
      {
        "neg": 0.0,
        "neu": 1.0,
        "pos": 0.0,
        "compound": 0.0
      }
    ],
    [
      "I remember going to @ BrooklynNets games in NJ watching @ RealJasonKidd and @ chibbs_1 ! So fun. My son tells me @ mrvincecarter15 is still playing!!!! Ahhhhmazing. I'm in awe!",
      {
        "neg": 0.0,
        "neu": 0.816,
        "pos": 0.184,
        "compound": 0.7513
      }
    ],
    [
      "\"Do not lay up treasure for yourselves on earth\" (Matthew 6:19) If I have one treasure on earth it would be for @ mrvincecarter15 to return to the Dunk contest^^ # returnofthechampion @ Raptors @ BrooklynNets @ OrlandoMagic @ Suns @ dallasmavs @ memgrizz @ SacramentoKings @ ATLHawks",
      {
        "neg": 0.097,
        "neu": 0.903,
        "pos": 0.0,
        "compound": -0.4168
      }
    ],
    [
      "Hangin tough @ DwyaneWade @ mrvincecarter15 https://twitter.com/espn/status/1059106445646553088 \u2026",
      {
        "neg": 0.273,
        "neu": 0.727,
        "pos": 0.0,
        "compound": -0.128
      }
    ],
    [
      "Players like @ JCrossover \u2014 @ drose & @ mrvincecarter15 really make basketball worth it. The time and energy put in the gym really makes a difference when your mindset is to get better with every effort.",
      {
        "neg": 0.0,
        "neu": 0.736,
        "pos": 0.264,
        "compound": 0.8255
      }
    ],
    [
      "Just going to get me all # Emo with this! @ mrvincecarter15 # VC15 @ DwyaneWade # DW3 Future # HOF # BetterLateThanNever seeing this for the first time (Homecoming weekend had me on lock)https://twitter.com/BSHighlights/status/1058943056253198336 \u2026",
      {
        "neg": 0.0,
        "neu": 1.0,
        "pos": 0.0,
        "compound": 0.0
      }
    ],
    [
      "I seen @ drose drop 50 this season now all I need is @ mrvincecarter15 to honey dip one more time and my nba season will be complete",
      {
        "neg": 0.084,
        "neu": 0.916,
        "pos": 0.0,
        "compound": -0.2732
      }
    ],
    [
      "super dopeness",
      {
        "neg": 0.0,
        "neu": 0.204,
        "pos": 0.796,
        "compound": 0.5994
      }
    ],
    [
      "@ NBA yall better quit playing and put @ mrvincecarter15 in the dunk contest this year!",
      {
        "neg": 0.0,
        "neu": 0.706,
        "pos": 0.294,
        "compound": 0.6114
      }
    ],
    [
      "2 Future @ NBA Hall of Famer\u2019s @ DwyaneWade & @ mrvincecarter15 https://twitter.com/espn/status/1059106445646553088 \u2026",
      {
        "neg": 0.0,
        "neu": 1.0,
        "pos": 0.0,
        "compound": 0.0
      }
    ],
    [
      "@ Bigfredstyle",
      {
        "neg": 0.0,
        "neu": 1.0,
        "pos": 0.0,
        "compound": 0.0
      }
    ],
    [
      "They're wack",
      {
        "neg": 0.0,
        "neu": 1.0,
        "pos": 0.0,
        "compound": 0.0
      }
    ],
    [
      "I still remember where i was when i saw it live :) even if france lose",
      {
        "neg": 0.162,
        "neu": 0.659,
        "pos": 0.18,
        "compound": 0.0772
      }
    ],
    [
      "@ NBA is there any way we can get @ mrvincecarter15 to participate in the dunk contest one last time??",
      {
        "neg": 0.0,
        "neu": 1.0,
        "pos": 0.0,
        "compound": 0.0
      }
    ],
    [
      "# espnnow Vince may no longer have Jordan-type ups but he still has hops of prime Josh Smith. # FlyLikeAHawk",
      {
        "neg": 0.086,
        "neu": 0.914,
        "pos": 0.0,
        "compound": -0.1531
      }
    ],
    [
      "Vince is trying to out last Dirk. Give it up Vince",
      {
        "neg": 0.0,
        "neu": 1.0,
        "pos": 0.0,
        "compound": 0.0
      }
    ],
    [
      "true kings",
      {
        "neg": 0.0,
        "neu": 0.263,
        "pos": 0.737,
        "compound": 0.4215
      }
    ],
    [
      "Two of the greatest players to play the game...",
      {
        "neg": 0.0,
        "neu": 0.515,
        "pos": 0.485,
        "compound": 0.765
      }
    ],
    [
      "I NEED THIS FRAMED. OMGGGGGG VINCE",
      {
        "neg": 0.0,
        "neu": 1.0,
        "pos": 0.0,
        "compound": 0.0
      }
    ],
    [
      "My fave player ever @ mrvincecarter15 https://twitter.com/NBA/status/1058942457960898560 \u2026",
      {
        "neg": 0.0,
        "neu": 0.633,
        "pos": 0.367,
        "compound": 0.4404
      }
    ],
    [
      "666",
      {
        "neg": 0.0,
        "neu": 1.0,
        "pos": 0.0,
        "compound": 0.0
      }
    ],
    [
      "Yo, KG was so hyped during and after this dunk. # Phenomenal",
      {
        "neg": 0.0,
        "neu": 1.0,
        "pos": 0.0,
        "compound": 0.0
      }
    ],
    [
      "pic.twitter.com/8myqBDalnJ",
      {
        "neg": 0.0,
        "neu": 1.0,
        "pos": 0.0,
        "compound": 0.0
      }
    ],
    [
      "He really did this effortlessly. Like the look in his face is like ehhhh he only 7 foot plus",
      {
        "neg": 0.0,
        "neu": 0.762,
        "pos": 0.238,
        "compound": 0.6124
      }
    ],
    [
      "OGs are still working the game plan!",
      {
        "neg": 0.0,
        "neu": 1.0,
        "pos": 0.0,
        "compound": 0.0
      }
    ],
    [
      "@ mrvincecarter15 my favorite player of ALL TIME!!! Vincent Lamar Carter!! The reason I decided to play bball...changed my life https://twitter.com/SLAMonline/status/1059178657116233728 \u2026",
      {
        "neg": 0.0,
        "neu": 0.721,
        "pos": 0.279,
        "compound": 0.7627
      }
    ],
    [
      "Eat it, Fr\u00e9d\u00e9ric Weis!",
      {
        "neg": 0.0,
        "neu": 1.0,
        "pos": 0.0,
        "compound": 0.0
      }
    ],
    [
      "pic.twitter.com/coBT6QmrLr",
      {
        "neg": 0.0,
        "neu": 1.0,
        "pos": 0.0,
        "compound": 0.0
      }
    ],
    [
      "Oh my godness",
      {
        "neg": 0.0,
        "neu": 1.0,
        "pos": 0.0,
        "compound": 0.0
      }
    ],
    [
      "@ NNiiiico",
      {
        "neg": 0.0,
        "neu": 1.0,
        "pos": 0.0,
        "compound": 0.0
      }
    ],
    [
      "Need both them jerseys",
      {
        "neg": 0.0,
        "neu": 1.0,
        "pos": 0.0,
        "compound": 0.0
      }
    ],
    [
      "Living Legends ?? # DwyaneWade # mrvincecarter15 # MiamiHEAT # ATLHawks # DwyaneWade # OneLastDance # VinceCarter # ATL # Miami # Mia\u2026 http://dlvr.it/QqRWCq",
      {
        "neg": 0.0,
        "neu": 1.0,
        "pos": 0.0,
        "compound": 0.0
      }
    ],
    [
      "Not only is @ mrvincecarter15 the oldest active NBA player, but @ juliuspeppers_ is the oldest active NFL player that\u2019s not a QB or kicker. Two Tar Heel legends that are still performing at the highest level.",
      {
        "neg": 0.0,
        "neu": 0.856,
        "pos": 0.144,
        "compound": 0.6597
      }
    ],
    2018,
    29
  ]
}